<?xml version="1.0" encoding="UTF-8"?>
<PeakList>
  <PeakList1D>
    <PeakList1DHeader creator="NMR User1" date="2022-09-27T13:35:38.854+08:00" expNo="10" name="TP13" owner="" procNo="1" source="C:/Bruker/TopSpin3.2/data/May 2014/2-Balamurugan">
      <PeakPickDetails>F1=15.472480ppm, F2=-1.504001ppm, MI=0.00cm, MAXI=10000.00cm, PC=1.000
      </PeakPickDetails>
    </PeakList1DHeader>
    <Peak1D F1="8.252447" intensity="9.339884e-003" type="0"/>
    <Peak1D F1="8.116367" intensity="3.082925e-003" type="0"/>
    <Peak1D F1="8.015770" intensity="1.557487e+000" type="0"/>
    <Peak1D F1="7.774052" intensity="9.099114e-003" type="0"/>
    <Peak1D F1="7.612543" intensity="3.194753e-003" type="0"/>
    <Peak1D F1="7.593120" intensity="4.690398e-003" type="0"/>
    <Peak1D F1="7.538422" intensity="3.067294e-003" type="0"/>
    <Peak1D F1="7.526410" intensity="2.122749e-002" type="0"/>
    <Peak1D F1="7.520771" intensity="5.306948e-003" type="0"/>
    <Peak1D F1="7.502689" intensity="3.962690e-003" type="0"/>
    <Peak1D F1="7.498818" intensity="3.967175e-003" type="0"/>
    <Peak1D F1="7.467766" intensity="3.887115e-003" type="0"/>
    <Peak1D F1="7.449313" intensity="6.215749e-003" type="0"/>
    <Peak1D F1="7.444436" intensity="5.717376e-003" type="0"/>
    <Peak1D F1="7.422382" intensity="4.042723e-001" type="0"/>
    <Peak1D F1="7.421586" intensity="4.011982e-001" type="0"/>
    <Peak1D F1="7.417906" intensity="5.784782e-001" type="0"/>
    <Peak1D F1="7.413665" intensity="1.652522e-001" type="0"/>
    <Peak1D F1="7.400419" intensity="8.191606e-001" type="0"/>
    <Peak1D F1="7.398520" intensity="7.214882e-001" type="0"/>
    <Peak1D F1="7.393395" intensity="1.006261e-001" type="0"/>
    <Peak1D F1="7.343367" intensity="2.944031e-001" type="0"/>
    <Peak1D F1="7.341014" intensity="4.696652e-001" type="0"/>
    <Peak1D F1="7.336533" intensity="1.550857e-001" type="0"/>
    <Peak1D F1="7.323109" intensity="9.329331e-001" type="0"/>
    <Peak1D F1="7.319393" intensity="3.921311e-001" type="0"/>
    <Peak1D F1="7.307567" intensity="2.389712e-001" type="0"/>
    <Peak1D F1="7.304208" intensity="4.639167e-001" type="0"/>
    <Peak1D F1="7.299285" intensity="7.464857e-002" type="0"/>
    <Peak1D F1="7.293535" intensity="1.666435e-002" type="0"/>
    <Peak1D F1="7.291248" intensity="8.918818e-003" type="0"/>
    <Peak1D F1="7.289379" intensity="1.269523e-002" type="0"/>
    <Peak1D F1="7.267509" intensity="3.881055e+000" type="0"/>
    <Peak1D F1="7.262918" intensity="2.444380e-001" type="0"/>
    <Peak1D F1="7.253667" intensity="1.411594e-001" type="0"/>
    <Peak1D F1="7.247982" intensity="4.165522e-001" type="0"/>
    <Peak1D F1="7.242210" intensity="9.311248e-002" type="0"/>
    <Peak1D F1="7.233254" intensity="8.059486e-002" type="0"/>
    <Peak1D F1="7.229937" intensity="1.365874e-001" type="0"/>
    <Peak1D F1="7.226641" intensity="6.785247e-002" type="0"/>
    <Peak1D F1="7.216908" intensity="4.675866e-003" type="0"/>
    <Peak1D F1="7.121906" intensity="3.198544e-003" type="0"/>
    <Peak1D F1="7.003497" intensity="1.959448e-002" type="0"/>
    <Peak1D F1="6.769008" intensity="8.141033e-003" type="0"/>
    <Peak1D F1="6.756406" intensity="2.787729e-001" type="0"/>
    <Peak1D F1="6.729199" intensity="2.914916e-001" type="0"/>
    <Peak1D F1="6.712401" intensity="3.072678e-001" type="0"/>
    <Peak1D F1="6.685199" intensity="3.156998e-001" type="0"/>
    <Peak1D F1="6.600438" intensity="5.125372e-003" type="0"/>
    <Peak1D F1="6.573595" intensity="4.925926e-003" type="0"/>
    <Peak1D F1="6.556270" intensity="5.669281e-003" type="0"/>
    <Peak1D F1="6.529423" intensity="6.616462e-003" type="0"/>
    <Peak1D F1="6.515360" intensity="2.369128e-002" type="0"/>
    <Peak1D F1="6.490680" intensity="3.724030e-003" type="0"/>
    <Peak1D F1="6.462889" intensity="3.074449e-003" type="0"/>
    <Peak1D F1="6.434925" intensity="6.066665e-003" type="0"/>
    <Peak1D F1="6.426578" intensity="9.563216e-003" type="0"/>
    <Peak1D F1="6.412057" intensity="7.176647e-001" type="0"/>
    <Peak1D F1="6.399983" intensity="1.745079e-002" type="0"/>
    <Peak1D F1="6.385011" intensity="7.555134e-001" type="0"/>
    <Peak1D F1="6.384270" intensity="7.446220e-001" type="0"/>
    <Peak1D F1="6.368037" intensity="7.900561e-001" type="0"/>
    <Peak1D F1="6.367188" intensity="7.706243e-001" type="0"/>
    <Peak1D F1="6.355783" intensity="1.937497e-002" type="0"/>
    <Peak1D F1="6.340958" intensity="8.164716e-001" type="0"/>
    <Peak1D F1="6.317021" intensity="4.261013e+000" type="0"/>
    <Peak1D F1="6.315878" intensity="3.887629e+000" type="0"/>
    <Peak1D F1="6.314401" intensity="4.151072e+000" type="0"/>
    <Peak1D F1="6.293778" intensity="9.428635e-003" type="0"/>
    <Peak1D F1="6.289910" intensity="5.579557e-003" type="0"/>
    <Peak1D F1="6.278281" intensity="4.552716e-003" type="0"/>
    <Peak1D F1="6.226193" intensity="5.483758e-003" type="0"/>
    <Peak1D F1="6.219337" intensity="3.250860e-003" type="0"/>
    <Peak1D F1="6.191676" intensity="3.823103e-003" type="0"/>
    <Peak1D F1="6.175122" intensity="4.255778e-003" type="0"/>
    <Peak1D F1="6.147859" intensity="4.161588e-003" type="0"/>
    <Peak1D F1="6.111846" intensity="2.253262e-002" type="0"/>
    <Peak1D F1="5.961641" intensity="4.192394e-003" type="0"/>
    <Peak1D F1="5.959226" intensity="4.207452e-003" type="0"/>
    <Peak1D F1="5.917634" intensity="4.047405e-003" type="0"/>
    <Peak1D F1="5.915325" intensity="3.983199e-003" type="0"/>
    <Peak1D F1="5.879140" intensity="1.998504e-002" type="0"/>
    <Peak1D F1="5.876366" intensity="2.111395e-002" type="0"/>
    <Peak1D F1="5.796946" intensity="5.026933e-003" type="0"/>
    <Peak1D F1="5.790425" intensity="4.787656e-003" type="0"/>
    <Peak1D F1="5.770832" intensity="6.225113e-001" type="0"/>
    <Peak1D F1="5.768517" intensity="6.157401e-001" type="0"/>
    <Peak1D F1="5.760734" intensity="1.247043e-002" type="0"/>
    <Peak1D F1="5.753015" intensity="7.948590e-003" type="0"/>
    <Peak1D F1="5.750292" intensity="7.215518e-003" type="0"/>
    <Peak1D F1="5.746316" intensity="5.523325e-003" type="0"/>
    <Peak1D F1="5.726832" intensity="5.757982e-001" type="0"/>
    <Peak1D F1="5.724514" intensity="5.628057e-001" type="0"/>
    <Peak1D F1="5.711605" intensity="1.668125e-002" type="0"/>
    <Peak1D F1="5.708703" intensity="2.040333e-002" type="0"/>
    <Peak1D F1="5.705537" intensity="2.245048e-002" type="0"/>
    <Peak1D F1="5.701553" intensity="3.256976e-002" type="0"/>
    <Peak1D F1="5.698532" intensity="5.412569e-002" type="0"/>
    <Peak1D F1="5.695507" intensity="6.873795e-002" type="0"/>
    <Peak1D F1="5.685624" intensity="1.637539e+000" type="0"/>
    <Peak1D F1="5.682858" intensity="4.220932e+000" type="0"/>
    <Peak1D F1="5.680015" intensity="4.141798e+000" type="0"/>
    <Peak1D F1="5.677243" intensity="1.525840e+000" type="0"/>
    <Peak1D F1="5.667135" intensity="5.308033e-002" type="0"/>
    <Peak1D F1="5.664299" intensity="4.081081e-002" type="0"/>
    <Peak1D F1="5.655559" intensity="9.159608e-003" type="0"/>
    <Peak1D F1="5.652544" intensity="4.106014e-003" type="0"/>
    <Peak1D F1="5.647089" intensity="4.671201e-003" type="0"/>
    <Peak1D F1="5.644426" intensity="5.162381e-003" type="0"/>
    <Peak1D F1="5.617369" intensity="3.389600e-003" type="0"/>
    <Peak1D F1="5.575725" intensity="4.400488e-003" type="0"/>
    <Peak1D F1="5.531660" intensity="3.443130e-003" type="0"/>
    <Peak1D F1="5.529305" intensity="3.390782e-003" type="0"/>
    <Peak1D F1="5.481987" intensity="2.094938e-002" type="0"/>
    <Peak1D F1="5.479211" intensity="1.937142e-002" type="0"/>
    <Peak1D F1="5.453779" intensity="1.041611e-002" type="0"/>
    <Peak1D F1="5.424653" intensity="5.030272e-003" type="0"/>
    <Peak1D F1="5.410795" intensity="1.083577e-002" type="0"/>
    <Peak1D F1="5.397174" intensity="8.346006e-003" type="0"/>
    <Peak1D F1="5.355130" intensity="4.233341e-003" type="0"/>
    <Peak1D F1="5.338389" intensity="6.842749e-003" type="0"/>
    <Peak1D F1="5.321081" intensity="5.118145e-003" type="0"/>
    <Peak1D F1="5.265303" intensity="1.180001e+000" type="0"/>
    <Peak1D F1="5.264026" intensity="1.259324e+000" type="0"/>
    <Peak1D F1="5.262691" intensity="1.188489e+000" type="0"/>
    <Peak1D F1="5.255970" intensity="5.996146e-001" type="0"/>
    <Peak1D F1="5.253719" intensity="5.699509e-001" type="0"/>
    <Peak1D F1="5.240839" intensity="2.730634e-002" type="0"/>
    <Peak1D F1="5.228737" intensity="5.935108e-001" type="0"/>
    <Peak1D F1="5.226467" intensity="6.093773e-001" type="0"/>
    <Peak1D F1="5.221286" intensity="1.106010e+000" type="0"/>
    <Peak1D F1="5.220004" intensity="1.165790e+000" type="0"/>
    <Peak1D F1="5.218686" intensity="1.086536e+000" type="0"/>
    <Peak1D F1="5.176671" intensity="1.298620e-001" type="0"/>
    <Peak1D F1="5.173234" intensity="2.710939e-001" type="0"/>
    <Peak1D F1="5.169697" intensity="3.493851e-001" type="0"/>
    <Peak1D F1="5.166163" intensity="2.873486e-001" type="0"/>
    <Peak1D F1="5.162594" intensity="2.075985e-001" type="0"/>
    <Peak1D F1="5.159601" intensity="2.952700e-001" type="0"/>
    <Peak1D F1="5.156134" intensity="5.401604e-001" type="0"/>
    <Peak1D F1="5.152668" intensity="6.970083e-001" type="0"/>
    <Peak1D F1="5.149160" intensity="5.833009e-001" type="0"/>
    <Peak1D F1="5.145575" intensity="3.581421e-001" type="0"/>
    <Peak1D F1="5.142311" intensity="2.760965e-001" type="0"/>
    <Peak1D F1="5.139098" intensity="3.329647e-001" type="0"/>
    <Peak1D F1="5.135616" intensity="3.290798e-001" type="0"/>
    <Peak1D F1="5.132055" intensity="2.179351e-001" type="0"/>
    <Peak1D F1="5.128612" intensity="9.728508e-002" type="0"/>
    <Peak1D F1="5.107864" intensity="1.110012e-002" type="0"/>
    <Peak1D F1="5.096874" intensity="1.264605e-002" type="0"/>
    <Peak1D F1="5.070452" intensity="5.218924e-001" type="0"/>
    <Peak1D F1="5.067498" intensity="9.989828e-001" type="0"/>
    <Peak1D F1="5.065859" intensity="1.042396e+000" type="0"/>
    <Peak1D F1="5.062927" intensity="5.418193e-001" type="0"/>
    <Peak1D F1="5.043340" intensity="4.817624e-001" type="0"/>
    <Peak1D F1="5.040503" intensity="9.453849e-001" type="0"/>
    <Peak1D F1="5.038824" intensity="1.019712e+000" type="0"/>
    <Peak1D F1="5.035909" intensity="5.480604e-001" type="0"/>
    <Peak1D F1="5.012996" intensity="1.726865e+000" type="0"/>
    <Peak1D F1="4.998228" intensity="1.280712e+000" type="0"/>
    <Peak1D F1="4.995519" intensity="1.397781e+000" type="0"/>
    <Peak1D F1="4.966482" intensity="5.570990e-003" type="0"/>
    <Peak1D F1="4.962743" intensity="6.060669e-003" type="0"/>
    <Peak1D F1="4.959156" intensity="5.520165e-003" type="0"/>
    <Peak1D F1="4.867779" intensity="7.667703e-003" type="0"/>
    <Peak1D F1="4.836754" intensity="1.183289e-002" type="0"/>
    <Peak1D F1="4.832008" intensity="9.338639e-003" type="0"/>
    <Peak1D F1="4.825995" intensity="8.153570e-003" type="0"/>
    <Peak1D F1="4.821281" intensity="1.004235e-002" type="0"/>
    <Peak1D F1="4.816005" intensity="1.054263e-002" type="0"/>
    <Peak1D F1="4.799389" intensity="1.222012e-002" type="0"/>
    <Peak1D F1="4.796271" intensity="1.447547e-002" type="0"/>
    <Peak1D F1="4.793797" intensity="1.326786e-002" type="0"/>
    <Peak1D F1="4.767549" intensity="7.317111e-003" type="0"/>
    <Peak1D F1="4.756554" intensity="8.591676e-003" type="0"/>
    <Peak1D F1="4.753094" intensity="7.370014e-003" type="0"/>
    <Peak1D F1="4.702825" intensity="3.022608e-002" type="0"/>
    <Peak1D F1="4.700517" intensity="2.089334e-002" type="0"/>
    <Peak1D F1="4.684162" intensity="1.890633e-001" type="0"/>
    <Peak1D F1="4.682195" intensity="2.215158e-001" type="0"/>
    <Peak1D F1="4.679662" intensity="1.861244e-001" type="0"/>
    <Peak1D F1="4.662360" intensity="1.182968e-002" type="0"/>
    <Peak1D F1="4.618741" intensity="1.384967e-001" type="0"/>
    <Peak1D F1="4.614537" intensity="2.566635e-001" type="0"/>
    <Peak1D F1="4.610312" intensity="1.328728e-001" type="0"/>
    <Peak1D F1="4.359825" intensity="2.282870e-002" type="0"/>
    <Peak1D F1="4.343306" intensity="4.470982e-002" type="0"/>
    <Peak1D F1="4.326766" intensity="2.340389e-002" type="0"/>
    <Peak1D F1="4.291650" intensity="2.258512e-002" type="0"/>
    <Peak1D F1="4.275060" intensity="4.619687e-002" type="0"/>
    <Peak1D F1="4.258590" intensity="2.771947e-002" type="0"/>
    <Peak1D F1="4.243288" intensity="8.571361e-003" type="0"/>
    <Peak1D F1="4.239398" intensity="7.383559e-003" type="0"/>
    <Peak1D F1="4.235224" intensity="9.834462e-003" type="0"/>
    <Peak1D F1="4.229051" intensity="9.274867e-003" type="0"/>
    <Peak1D F1="4.214429" intensity="1.687260e-002" type="0"/>
    <Peak1D F1="4.212179" intensity="1.682649e-002" type="0"/>
    <Peak1D F1="4.204905" intensity="2.057160e-002" type="0"/>
    <Peak1D F1="4.187903" intensity="8.809928e-002" type="0"/>
    <Peak1D F1="4.179060" intensity="4.183990e+000" type="0"/>
    <Peak1D F1="4.162521" intensity="8.596446e+000" type="0"/>
    <Peak1D F1="4.145961" intensity="4.236556e+000" type="0"/>
    <Peak1D F1="4.135138" intensity="4.302998e-002" type="0"/>
    <Peak1D F1="4.126420" intensity="4.305838e-002" type="0"/>
    <Peak1D F1="4.111058" intensity="3.845243e+000" type="0"/>
    <Peak1D F1="4.094380" intensity="7.857862e+000" type="0"/>
    <Peak1D F1="4.077678" intensity="3.892205e+000" type="0"/>
    <Peak1D F1="4.067064" intensity="3.452871e-002" type="0"/>
    <Peak1D F1="4.053504" intensity="1.197268e-002" type="0"/>
    <Peak1D F1="4.050448" intensity="6.423586e-003" type="0"/>
    <Peak1D F1="4.031203" intensity="4.613245e-003" type="0"/>
    <Peak1D F1="3.992948" intensity="2.112739e-002" type="0"/>
    <Peak1D F1="3.976398" intensity="4.263201e-002" type="0"/>
    <Peak1D F1="3.959853" intensity="2.072727e-002" type="0"/>
    <Peak1D F1="3.925163" intensity="1.916746e-002" type="0"/>
    <Peak1D F1="3.908474" intensity="4.013921e-002" type="0"/>
    <Peak1D F1="3.891773" intensity="1.986019e-002" type="0"/>
    <Peak1D F1="3.671363" intensity="3.244524e-003" type="0"/>
    <Peak1D F1="3.654977" intensity="6.650395e-003" type="0"/>
    <Peak1D F1="3.641669" intensity="6.628338e-003" type="0"/>
    <Peak1D F1="3.624992" intensity="3.780321e-003" type="0"/>
    <Peak1D F1="3.619508" intensity="5.134710e-003" type="0"/>
    <Peak1D F1="3.608410" intensity="5.716141e-003" type="0"/>
    <Peak1D F1="3.605959" intensity="5.845275e-003" type="0"/>
    <Peak1D F1="3.592769" intensity="5.521527e-003" type="0"/>
    <Peak1D F1="3.492285" intensity="4.365603e-002" type="0"/>
    <Peak1D F1="3.490209" intensity="4.329731e-002" type="0"/>
    <Peak1D F1="3.452464" intensity="3.703251e-003" type="0"/>
    <Peak1D F1="3.430691" intensity="4.475823e-003" type="0"/>
    <Peak1D F1="3.418688" intensity="5.438778e-003" type="0"/>
    <Peak1D F1="3.416259" intensity="5.469242e-003" type="0"/>
    <Peak1D F1="3.402127" intensity="1.359010e-002" type="0"/>
    <Peak1D F1="3.383494" intensity="1.387724e-002" type="0"/>
    <Peak1D F1="3.357992" intensity="3.280276e-002" type="0"/>
    <Peak1D F1="3.354470" intensity="3.524732e-002" type="0"/>
    <Peak1D F1="3.331584" intensity="8.130944e+000" type="0"/>
    <Peak1D F1="3.329402" intensity="7.932117e+000" type="0"/>
    <Peak1D F1="3.304811" intensity="1.922948e-002" type="0"/>
    <Peak1D F1="3.300780" intensity="8.727569e-003" type="0"/>
    <Peak1D F1="3.292937" intensity="1.285537e-002" type="0"/>
    <Peak1D F1="3.266997" intensity="6.491018e-003" type="0"/>
    <Peak1D F1="3.246952" intensity="3.456440e-003" type="0"/>
    <Peak1D F1="3.167233" intensity="4.377105e-002" type="0"/>
    <Peak1D F1="3.165217" intensity="4.258026e-002" type="0"/>
    <Peak1D F1="3.123177" intensity="8.313192e-002" type="0"/>
    <Peak1D F1="3.106149" intensity="3.874656e-003" type="0"/>
    <Peak1D F1="3.100368" intensity="3.751392e-003" type="0"/>
    <Peak1D F1="3.092795" intensity="3.180156e-003" type="0"/>
    <Peak1D F1="3.084185" intensity="5.214669e-003" type="0"/>
    <Peak1D F1="3.073672" intensity="5.233014e-003" type="0"/>
    <Peak1D F1="3.053123" intensity="7.662266e-002" type="0"/>
    <Peak1D F1="3.051783" intensity="7.457064e-002" type="0"/>
    <Peak1D F1="3.031184" intensity="6.027055e-003" type="0"/>
    <Peak1D F1="3.026484" intensity="1.001222e-002" type="0"/>
    <Peak1D F1="3.021405" intensity="7.143693e-003" type="0"/>
    <Peak1D F1="3.007639" intensity="1.257808e-002" type="0"/>
    <Peak1D F1="3.003158" intensity="1.647791e-002" type="0"/>
    <Peak1D F1="2.999204" intensity="8.374183e-003" type="0"/>
    <Peak1D F1="2.992004" intensity="1.001226e-002" type="0"/>
    <Peak1D F1="2.983106" intensity="2.808061e-002" type="0"/>
    <Peak1D F1="2.979833" intensity="4.137044e-002" type="0"/>
    <Peak1D F1="2.975208" intensity="3.897310e-002" type="0"/>
    <Peak1D F1="2.953532" intensity="1.500000e+001" type="0"/>
    <Peak1D F1="2.942859" intensity="1.017859e-001" type="0"/>
    <Peak1D F1="2.935226" intensity="4.314472e-002" type="0"/>
    <Peak1D F1="2.929818" intensity="3.956559e-002" type="0"/>
    <Peak1D F1="2.925905" intensity="1.486983e-002" type="0"/>
    <Peak1D F1="2.920232" intensity="1.492004e-002" type="0"/>
    <Peak1D F1="2.917218" intensity="2.163190e-002" type="0"/>
    <Peak1D F1="2.911168" intensity="3.405931e-002" type="0"/>
    <Peak1D F1="2.908417" intensity="4.044460e-002" type="0"/>
    <Peak1D F1="2.906665" intensity="3.437033e-002" type="0"/>
    <Peak1D F1="2.904277" intensity="2.992284e-002" type="0"/>
    <Peak1D F1="2.902760" intensity="3.606142e-002" type="0"/>
    <Peak1D F1="2.896665" intensity="6.250902e-002" type="0"/>
    <Peak1D F1="2.882444" intensity="1.307016e+001" type="0"/>
    <Peak1D F1="2.881082" intensity="1.290762e+001" type="0"/>
    <Peak1D F1="2.870682" intensity="9.322629e-002" type="0"/>
    <Peak1D F1="2.863051" intensity="3.404516e-002" type="0"/>
    <Peak1D F1="2.859827" intensity="1.766008e-002" type="0"/>
    <Peak1D F1="2.857913" intensity="3.081259e-002" type="0"/>
    <Peak1D F1="2.853662" intensity="9.955009e-003" type="0"/>
    <Peak1D F1="2.849305" intensity="9.441619e-003" type="0"/>
    <Peak1D F1="2.845168" intensity="1.306187e-002" type="0"/>
    <Peak1D F1="2.842465" intensity="1.054374e-002" type="0"/>
    <Peak1D F1="2.839219" intensity="1.125778e-002" type="0"/>
    <Peak1D F1="2.835130" intensity="8.849516e-003" type="0"/>
    <Peak1D F1="2.817402" intensity="7.879910e-003" type="0"/>
    <Peak1D F1="2.792608" intensity="4.602999e-003" type="0"/>
    <Peak1D F1="2.779592" intensity="8.187783e-002" type="0"/>
    <Peak1D F1="2.771720" intensity="5.099035e-003" type="0"/>
    <Peak1D F1="2.750403" intensity="3.091171e-003" type="0"/>
    <Peak1D F1="2.707479" intensity="7.127552e-002" type="0"/>
    <Peak1D F1="2.706111" intensity="7.149103e-002" type="0"/>
    <Peak1D F1="2.658568" intensity="3.892023e-003" type="0"/>
    <Peak1D F1="2.638497" intensity="4.617495e-003" type="0"/>
    <Peak1D F1="2.619524" intensity="1.421934e-002" type="0"/>
    <Peak1D F1="2.596957" intensity="4.342108e-003" type="0"/>
    <Peak1D F1="2.583032" intensity="4.130108e-003" type="0"/>
    <Peak1D F1="2.554745" intensity="4.629822e-003" type="0"/>
    <Peak1D F1="2.531961" intensity="4.500588e-003" type="0"/>
    <Peak1D F1="2.514431" intensity="4.093476e-003" type="0"/>
    <Peak1D F1="2.494129" intensity="3.319276e-003" type="0"/>
    <Peak1D F1="2.451701" intensity="3.182979e-003" type="0"/>
    <Peak1D F1="2.442791" intensity="3.402564e-003" type="0"/>
    <Peak1D F1="2.437915" intensity="3.620042e-003" type="0"/>
    <Peak1D F1="2.431788" intensity="3.802916e-003" type="0"/>
    <Peak1D F1="2.422771" intensity="3.499812e-003" type="0"/>
    <Peak1D F1="2.419015" intensity="3.830972e-003" type="0"/>
    <Peak1D F1="2.409286" intensity="2.172694e-002" type="0"/>
    <Peak1D F1="2.400908" intensity="6.858490e-003" type="0"/>
    <Peak1D F1="2.382776" intensity="1.228162e-002" type="0"/>
    <Peak1D F1="2.370140" intensity="3.059505e-002" type="0"/>
    <Peak1D F1="2.360768" intensity="6.361283e-002" type="0"/>
    <Peak1D F1="2.355587" intensity="4.252468e-002" type="0"/>
    <Peak1D F1="2.332366" intensity="5.373687e-002" type="0"/>
    <Peak1D F1="2.327362" intensity="7.761295e-002" type="0"/>
    <Peak1D F1="2.322320" intensity="5.309545e-002" type="0"/>
    <Peak1D F1="2.306671" intensity="1.182770e-002" type="0"/>
    <Peak1D F1="2.300348" intensity="9.776962e-003" type="0"/>
    <Peak1D F1="2.295636" intensity="9.109278e-003" type="0"/>
    <Peak1D F1="2.287192" intensity="2.677162e-002" type="0"/>
    <Peak1D F1="2.283276" intensity="2.824759e-002" type="0"/>
    <Peak1D F1="2.250757" intensity="2.233587e-001" type="0"/>
    <Peak1D F1="2.243175" intensity="3.098629e-001" type="0"/>
    <Peak1D F1="2.240344" intensity="3.745271e-001" type="0"/>
    <Peak1D F1="2.235418" intensity="2.742741e-001" type="0"/>
    <Peak1D F1="2.226732" intensity="8.470096e-001" type="0"/>
    <Peak1D F1="2.221290" intensity="8.886393e-001" type="0"/>
    <Peak1D F1="2.218269" intensity="7.759106e-001" type="0"/>
    <Peak1D F1="2.209502" intensity="1.930716e+000" type="0"/>
    <Peak1D F1="2.199675" intensity="9.585678e-001" type="0"/>
    <Peak1D F1="2.184836" intensity="1.014650e+000" type="0"/>
    <Peak1D F1="2.169509" intensity="5.416752e-001" type="0"/>
    <Peak1D F1="2.150193" intensity="1.516336e-001" type="0"/>
    <Peak1D F1="2.147527" intensity="1.477814e-001" type="0"/>
    <Peak1D F1="2.145154" intensity="1.385881e-001" type="0"/>
    <Peak1D F1="2.125200" intensity="1.452059e-002" type="0"/>
    <Peak1D F1="2.103276" intensity="3.979380e-002" type="0"/>
    <Peak1D F1="2.095508" intensity="3.732502e-002" type="0"/>
    <Peak1D F1="2.071953" intensity="7.321905e-002" type="0"/>
    <Peak1D F1="2.064290" intensity="6.466334e-002" type="0"/>
    <Peak1D F1="2.061023" intensity="7.085581e-002" type="0"/>
    <Peak1D F1="2.050200" intensity="3.546250e-002" type="0"/>
    <Peak1D F1="2.041824" intensity="6.550472e-002" type="0"/>
    <Peak1D F1="2.032942" intensity="4.918174e-002" type="0"/>
    <Peak1D F1="2.011811" intensity="3.058034e-002" type="0"/>
    <Peak1D F1="2.004778" intensity="4.014486e-002" type="0"/>
    <Peak1D F1="1.989108" intensity="2.730815e-002" type="0"/>
    <Peak1D F1="1.960455" intensity="1.352702e-002" type="0"/>
    <Peak1D F1="1.938356" intensity="9.075249e-003" type="0"/>
    <Peak1D F1="1.919645" intensity="1.019570e-002" type="0"/>
    <Peak1D F1="1.915334" intensity="9.637188e-003" type="0"/>
    <Peak1D F1="1.905931" intensity="8.740299e-003" type="0"/>
    <Peak1D F1="1.900074" intensity="8.311751e-003" type="0"/>
    <Peak1D F1="1.862068" intensity="4.528471e-002" type="0"/>
    <Peak1D F1="1.853205" intensity="5.706711e-002" type="0"/>
    <Peak1D F1="1.850017" intensity="5.519150e-002" type="0"/>
    <Peak1D F1="1.836418" intensity="3.891487e-002" type="0"/>
    <Peak1D F1="1.830343" intensity="5.155857e-002" type="0"/>
    <Peak1D F1="1.823914" intensity="5.573010e-002" type="0"/>
    <Peak1D F1="1.804165" intensity="2.694995e-002" type="0"/>
    <Peak1D F1="1.801008" intensity="2.237738e-002" type="0"/>
    <Peak1D F1="1.796133" intensity="1.642410e-002" type="0"/>
    <Peak1D F1="1.784847" intensity="2.314447e-002" type="0"/>
    <Peak1D F1="1.779228" intensity="2.548073e-002" type="0"/>
    <Peak1D F1="1.764318" intensity="5.940335e-002" type="0"/>
    <Peak1D F1="1.748869" intensity="3.150538e-002" type="0"/>
    <Peak1D F1="1.741458" intensity="3.087257e-002" type="0"/>
    <Peak1D F1="1.734502" intensity="5.949738e-002" type="0"/>
    <Peak1D F1="1.732143" intensity="8.585549e-002" type="0"/>
    <Peak1D F1="1.729407" intensity="7.568167e-002" type="0"/>
    <Peak1D F1="1.723690" intensity="2.047579e-001" type="0"/>
    <Peak1D F1="1.716674" intensity="3.216469e-001" type="0"/>
    <Peak1D F1="1.713996" intensity="5.396342e-001" type="0"/>
    <Peak1D F1="1.711348" intensity="3.686286e-001" type="0"/>
    <Peak1D F1="1.697782" intensity="5.091771e+000" type="0"/>
    <Peak1D F1="1.695239" intensity="4.945273e+000" type="0"/>
    <Peak1D F1="1.683499" intensity="1.141907e+000" type="0"/>
    <Peak1D F1="1.678763" intensity="7.875600e+000" type="0"/>
    <Peak1D F1="1.667567" intensity="2.008563e+000" type="0"/>
    <Peak1D F1="1.666396" intensity="1.994509e+000" type="0"/>
    <Peak1D F1="1.659767" intensity="7.168536e-001" type="0"/>
    <Peak1D F1="1.651207" intensity="2.101201e+000" type="0"/>
    <Peak1D F1="1.649155" intensity="2.515198e+000" type="0"/>
    <Peak1D F1="1.646230" intensity="1.536680e+000" type="0"/>
    <Peak1D F1="1.643212" intensity="1.520107e+000" type="0"/>
    <Peak1D F1="1.641006" intensity="1.046550e+000" type="0"/>
    <Peak1D F1="1.634392" intensity="9.823125e-001" type="0"/>
    <Peak1D F1="1.629416" intensity="2.355286e+000" type="0"/>
    <Peak1D F1="1.624419" intensity="2.191981e+000" type="0"/>
    <Peak1D F1="1.622962" intensity="2.208583e+000" type="0"/>
    <Peak1D F1="1.611440" intensity="6.307516e+000" type="0"/>
    <Peak1D F1="1.608286" intensity="6.693901e+000" type="0"/>
    <Peak1D F1="1.599922" intensity="1.589110e+000" type="0"/>
    <Peak1D F1="1.586190" intensity="2.173675e+000" type="0"/>
    <Peak1D F1="1.569459" intensity="9.876230e-001" type="0"/>
    <Peak1D F1="1.551094" intensity="2.966303e-002" type="0"/>
    <Peak1D F1="1.547403" intensity="3.187789e-002" type="0"/>
    <Peak1D F1="1.537471" intensity="4.926184e-002" type="0"/>
    <Peak1D F1="1.529899" intensity="2.633954e-002" type="0"/>
    <Peak1D F1="1.524808" intensity="2.161123e-002" type="0"/>
    <Peak1D F1="1.510530" intensity="2.263928e-002" type="0"/>
    <Peak1D F1="1.500238" intensity="1.421210e-002" type="0"/>
    <Peak1D F1="1.492152" intensity="2.441985e-002" type="0"/>
    <Peak1D F1="1.489637" intensity="2.081854e-002" type="0"/>
    <Peak1D F1="1.483640" intensity="1.793051e-002" type="0"/>
    <Peak1D F1="1.478001" intensity="2.206352e-002" type="0"/>
    <Peak1D F1="1.473039" intensity="2.104379e-002" type="0"/>
    <Peak1D F1="1.462748" intensity="2.484599e-002" type="0"/>
    <Peak1D F1="1.447275" intensity="5.356227e-001" type="0"/>
    <Peak1D F1="1.432823" intensity="3.950579e-001" type="0"/>
    <Peak1D F1="1.428673" intensity="1.656308e+000" type="0"/>
    <Peak1D F1="1.414790" intensity="1.389820e+000" type="0"/>
    <Peak1D F1="1.409668" intensity="2.419415e+000" type="0"/>
    <Peak1D F1="1.396333" intensity="2.531622e+000" type="0"/>
    <Peak1D F1="1.390768" intensity="2.665762e+000" type="0"/>
    <Peak1D F1="1.382267" intensity="1.083877e+000" type="0"/>
    <Peak1D F1="1.377516" intensity="2.734327e+000" type="0"/>
    <Peak1D F1="1.372764" intensity="2.037156e+000" type="0"/>
    <Peak1D F1="1.363804" intensity="1.028331e+000" type="0"/>
    <Peak1D F1="1.358509" intensity="2.484072e+000" type="0"/>
    <Peak1D F1="1.345530" intensity="4.462149e-001" type="0"/>
    <Peak1D F1="1.340261" intensity="1.570425e+000" type="0"/>
    <Peak1D F1="1.322018" intensity="4.825669e-001" type="0"/>
    <Peak1D F1="1.305028" intensity="5.760549e-002" type="0"/>
    <Peak1D F1="1.295561" intensity="5.508357e-002" type="0"/>
    <Peak1D F1="1.273857" intensity="5.403520e-002" type="0"/>
    <Peak1D F1="1.263963" intensity="5.466544e-002" type="0"/>
    <Peak1D F1="1.254741" intensity="6.421567e-002" type="0"/>
    <Peak1D F1="1.242697" intensity="2.898240e-002" type="0"/>
    <Peak1D F1="1.232489" intensity="3.803897e-002" type="0"/>
    <Peak1D F1="1.225413" intensity="1.503822e-002" type="0"/>
    <Peak1D F1="1.218653" intensity="1.882725e-002" type="0"/>
    <Peak1D F1="1.199735" intensity="1.625238e-002" type="0"/>
    <Peak1D F1="1.181483" intensity="1.208774e-002" type="0"/>
    <Peak1D F1="1.163686" intensity="5.894316e-003" type="0"/>
    <Peak1D F1="1.147910" intensity="3.180949e-003" type="0"/>
    <Peak1D F1="1.129977" intensity="3.546281e-003" type="0"/>
    <Peak1D F1="1.114256" intensity="3.517763e-002" type="0"/>
    <Peak1D F1="1.095956" intensity="7.302575e-002" type="0"/>
    <Peak1D F1="1.080552" intensity="7.132734e-002" type="0"/>
    <Peak1D F1="1.062151" intensity="2.865675e-002" type="0"/>
    <Peak1D F1="1.051176" intensity="5.622320e-003" type="0"/>
    <Peak1D F1="1.041020" intensity="7.625036e-003" type="0"/>
    <Peak1D F1="1.031737" intensity="4.041970e-002" type="0"/>
    <Peak1D F1="1.023364" intensity="1.260145e-001" type="0"/>
    <Peak1D F1="1.018171" intensity="1.792561e-002" type="0"/>
    <Peak1D F1="1.014680" intensity="4.546079e-002" type="0"/>
    <Peak1D F1="1.010338" intensity="1.409396e-002" type="0"/>
    <Peak1D F1="0.994271" intensity="2.148565e-002" type="0"/>
    <Peak1D F1="0.990883" intensity="1.975939e-002" type="0"/>
    <Peak1D F1="0.986057" intensity="2.480805e-002" type="0"/>
    <Peak1D F1="0.980620" intensity="3.704099e-002" type="0"/>
    <Peak1D F1="0.959976" intensity="6.544923e+000" type="0"/>
    <Peak1D F1="0.944546" intensity="7.748064e+000" type="0"/>
    <Peak1D F1="0.941576" intensity="1.413398e+001" type="0"/>
    <Peak1D F1="0.926226" intensity="1.407274e+001" type="0"/>
    <Peak1D F1="0.923210" intensity="6.512234e+000" type="0"/>
    <Peak1D F1="0.907782" intensity="5.414172e+000" type="0"/>
    <Peak1D F1="0.890401" intensity="4.280996e-002" type="0"/>
    <Peak1D F1="0.883478" intensity="3.768514e-002" type="0"/>
    <Peak1D F1="0.880043" intensity="3.835185e-002" type="0"/>
    <Peak1D F1="0.871272" intensity="1.993920e-002" type="0"/>
    <Peak1D F1="0.861079" intensity="1.836333e-002" type="0"/>
    <Peak1D F1="0.857215" intensity="1.364499e-002" type="0"/>
    <Peak1D F1="0.854559" intensity="1.324404e-002" type="0"/>
    <Peak1D F1="0.847858" intensity="8.462259e-003" type="0"/>
    <Peak1D F1="0.844323" intensity="8.954882e-003" type="0"/>
    <Peak1D F1="0.838062" intensity="8.980366e-003" type="0"/>
    <Peak1D F1="0.832466" intensity="6.599035e-003" type="0"/>
    <Peak1D F1="0.815337" intensity="6.203227e-002" type="0"/>
    <Peak1D F1="0.801947" intensity="4.079184e-002" type="0"/>
    <Peak1D F1="0.797487" intensity="6.230592e-002" type="0"/>
    <Peak1D F1="0.786557" intensity="4.475372e-002" type="0"/>
    <Peak1D F1="0.783547" intensity="7.988840e-002" type="0"/>
    <Peak1D F1="0.768201" intensity="8.178930e-002" type="0"/>
    <Peak1D F1="0.765112" intensity="4.712280e-002" type="0"/>
    <Peak1D F1="0.760554" intensity="1.478372e-001" type="0"/>
    <Peak1D F1="0.749800" intensity="3.418656e-002" type="0"/>
    <Peak1D F1="0.735237" intensity="6.584142e-003" type="0"/>
    <Peak1D F1="0.712905" intensity="1.056083e-002" type="0"/>
    <Peak1D F1="0.692571" intensity="9.501798e-003" type="0"/>
    <Peak1D F1="0.631814" intensity="8.758521e-003" type="0"/>
    <Peak1D F1="0.611863" intensity="9.477678e-003" type="0"/>
    <Peak1D F1="0.589858" intensity="5.389567e-003" type="0"/>
    <Peak1D F1="0.152360" intensity="3.063380e-003" type="0"/>
    <Peak1D F1="0.145954" intensity="2.579441e-002" type="0"/>
    <Peak1D F1="0.093449" intensity="2.544136e-002" type="0"/>
    <Peak1D F1="0.070667" intensity="1.349465e-002" type="0"/>
    <Peak1D F1="0.049353" intensity="4.216058e-003" type="0"/>
    <Peak1D F1="0.033901" intensity="3.129326e-003" type="0"/>
    <Peak1D F1="0.030024" intensity="6.222196e-003" type="0"/>
    <Peak1D F1="0.025751" intensity="1.527040e-002" type="0"/>
    <Peak1D F1="0.021744" intensity="1.314532e-002" type="0"/>
    <Peak1D F1="0.014071" intensity="1.931714e-002" type="0"/>
    <Peak1D F1="0.008049" intensity="2.584391e-001" type="0"/>
    <Peak1D F1="-0.000132" intensity="8.140597e+000" type="0"/>
    <Peak1D F1="-0.008430" intensity="2.415019e-001" type="0"/>
    <Peak1D F1="-0.018191" intensity="1.340591e-002" type="0"/>
    <Peak1D F1="-0.023385" intensity="1.006390e-002" type="0"/>
    <Peak1D F1="-0.024705" intensity="1.634370e-002" type="0"/>
    <Peak1D F1="-0.027386" intensity="7.268792e-003" type="0"/>
    <Peak1D F1="-0.032900" intensity="4.168828e-003" type="0"/>
    <Peak1D F1="-0.036033" intensity="6.403147e-003" type="0"/>
    <Peak1D F1="-0.038490" intensity="4.441672e-003" type="0"/>
    <Peak1D F1="-0.043380" intensity="4.759910e-003" type="0"/>
    <Peak1D F1="-0.046185" intensity="3.792448e-003" type="0"/>
    <Peak1D F1="-0.063317" intensity="3.111579e-003" type="0"/>
    <Peak1D F1="-0.149500" intensity="2.591795e-002" type="0"/>
  </PeakList1D>
</PeakList>
