<?xml version="1.0" encoding="UTF-8"?>
<PeakList>
  <PeakList1D>
    <PeakList1DHeader creator="NMR User1" date="2023-01-06T11:49:37.916+08:00" expNo="10" name="TP15R" owner="" procNo="1" source="C:/Bruker/TopSpin3.2/data/May 2014/2-Balamurugan">
      <PeakPickDetails>F1=15.488240ppm, F2=-1.488240ppm, MI=0.00cm, MAXI=10000.00cm, PC=1.000
      </PeakPickDetails>
    </PeakList1DHeader>
    <Peak1D F1="8.266854" intensity="8.324072e-003" type="0"/>
    <Peak1D F1="8.082512" intensity="1.940590e-002" type="0"/>
    <Peak1D F1="8.029496" intensity="1.594349e+000" type="0"/>
    <Peak1D F1="7.787330" intensity="7.991458e-003" type="0"/>
    <Peak1D F1="7.628067" intensity="7.576400e-003" type="0"/>
    <Peak1D F1="7.612175" intensity="6.025265e-003" type="0"/>
    <Peak1D F1="7.607222" intensity="1.184872e-002" type="0"/>
    <Peak1D F1="7.555840" intensity="2.668700e-003" type="0"/>
    <Peak1D F1="7.552392" intensity="5.624246e-003" type="0"/>
    <Peak1D F1="7.542177" intensity="1.514040e-002" type="0"/>
    <Peak1D F1="7.537792" intensity="7.023684e-003" type="0"/>
    <Peak1D F1="7.534473" intensity="1.239827e-002" type="0"/>
    <Peak1D F1="7.530752" intensity="7.295076e-003" type="0"/>
    <Peak1D F1="7.519831" intensity="3.054630e-003" type="0"/>
    <Peak1D F1="7.516558" intensity="7.572337e-003" type="0"/>
    <Peak1D F1="7.512744" intensity="5.969730e-003" type="0"/>
    <Peak1D F1="7.481595" intensity="3.110892e-003" type="0"/>
    <Peak1D F1="7.478289" intensity="3.242872e-003" type="0"/>
    <Peak1D F1="7.468376" intensity="3.637305e-003" type="0"/>
    <Peak1D F1="7.463428" intensity="1.054896e-002" type="0"/>
    <Peak1D F1="7.458657" intensity="8.033406e-003" type="0"/>
    <Peak1D F1="7.436348" intensity="1.306433e+000" type="0"/>
    <Peak1D F1="7.435678" intensity="1.300025e+000" type="0"/>
    <Peak1D F1="7.431977" intensity="1.905932e+000" type="0"/>
    <Peak1D F1="7.427701" intensity="5.438510e-001" type="0"/>
    <Peak1D F1="7.414443" intensity="2.694600e+000" type="0"/>
    <Peak1D F1="7.412601" intensity="2.415529e+000" type="0"/>
    <Peak1D F1="7.407435" intensity="3.494990e-001" type="0"/>
    <Peak1D F1="7.382030" intensity="1.236432e-002" type="0"/>
    <Peak1D F1="7.357205" intensity="9.564101e-001" type="0"/>
    <Peak1D F1="7.354831" intensity="1.541388e+000" type="0"/>
    <Peak1D F1="7.350345" intensity="5.072574e-001" type="0"/>
    <Peak1D F1="7.336951" intensity="3.083241e+000" type="0"/>
    <Peak1D F1="7.333227" intensity="1.317033e+000" type="0"/>
    <Peak1D F1="7.321382" intensity="7.842923e-001" type="0"/>
    <Peak1D F1="7.317895" intensity="1.549275e+000" type="0"/>
    <Peak1D F1="7.313090" intensity="2.552522e-001" type="0"/>
    <Peak1D F1="7.283228" intensity="3.666273e+000" type="0"/>
    <Peak1D F1="7.280074" intensity="1.318304e+000" type="0"/>
    <Peak1D F1="7.276597" intensity="6.600366e-001" type="0"/>
    <Peak1D F1="7.267438" intensity="4.471364e-001" type="0"/>
    <Peak1D F1="7.261782" intensity="1.388032e+000" type="0"/>
    <Peak1D F1="7.255927" intensity="3.193349e-001" type="0"/>
    <Peak1D F1="7.247035" intensity="2.719390e-001" type="0"/>
    <Peak1D F1="7.243737" intensity="4.581160e-001" type="0"/>
    <Peak1D F1="7.240453" intensity="2.344823e-001" type="0"/>
    <Peak1D F1="7.213228" intensity="1.373457e-002" type="0"/>
    <Peak1D F1="7.193709" intensity="3.282846e-003" type="0"/>
    <Peak1D F1="7.155936" intensity="8.260007e-003" type="0"/>
    <Peak1D F1="7.152857" intensity="1.190698e-002" type="0"/>
    <Peak1D F1="7.146039" intensity="4.206887e-003" type="0"/>
    <Peak1D F1="7.137691" intensity="1.187302e-002" type="0"/>
    <Peak1D F1="7.135007" intensity="1.357050e-002" type="0"/>
    <Peak1D F1="7.131731" intensity="9.812333e-003" type="0"/>
    <Peak1D F1="7.119505" intensity="5.425670e-003" type="0"/>
    <Peak1D F1="7.113347" intensity="6.358240e-003" type="0"/>
    <Peak1D F1="7.083348" intensity="3.638240e-003" type="0"/>
    <Peak1D F1="7.080197" intensity="5.618740e-003" type="0"/>
    <Peak1D F1="7.061856" intensity="8.546247e-003" type="0"/>
    <Peak1D F1="7.043583" intensity="4.111330e-003" type="0"/>
    <Peak1D F1="7.019112" intensity="1.625570e-002" type="0"/>
    <Peak1D F1="6.961014" intensity="5.044045e-003" type="0"/>
    <Peak1D F1="6.933737" intensity="5.252379e-003" type="0"/>
    <Peak1D F1="6.916651" intensity="5.509285e-003" type="0"/>
    <Peak1D F1="6.889888" intensity="5.794570e-003" type="0"/>
    <Peak1D F1="6.881265" intensity="2.924385e-003" type="0"/>
    <Peak1D F1="6.859061" intensity="9.517650e-003" type="0"/>
    <Peak1D F1="6.796614" intensity="2.485234e-003" type="0"/>
    <Peak1D F1="6.793711" intensity="4.382087e-003" type="0"/>
    <Peak1D F1="6.770437" intensity="9.192711e-001" type="0"/>
    <Peak1D F1="6.743231" intensity="9.577445e-001" type="0"/>
    <Peak1D F1="6.726436" intensity="1.014809e+000" type="0"/>
    <Peak1D F1="6.699227" intensity="1.041223e+000" type="0"/>
    <Peak1D F1="6.677191" intensity="4.689860e-003" type="0"/>
    <Peak1D F1="6.575997" intensity="5.300666e-003" type="0"/>
    <Peak1D F1="6.549055" intensity="5.244815e-003" type="0"/>
    <Peak1D F1="6.531995" intensity="2.668060e-002" type="0"/>
    <Peak1D F1="6.504856" intensity="5.206006e-003" type="0"/>
    <Peak1D F1="6.426589" intensity="2.344825e-001" type="0"/>
    <Peak1D F1="6.416052" intensity="1.155138e-002" type="0"/>
    <Peak1D F1="6.399538" intensity="2.472597e-001" type="0"/>
    <Peak1D F1="6.382584" intensity="2.602741e-001" type="0"/>
    <Peak1D F1="6.371658" intensity="1.664322e-002" type="0"/>
    <Peak1D F1="6.355546" intensity="2.749774e-001" type="0"/>
    <Peak1D F1="6.344008" intensity="8.282267e-002" type="0"/>
    <Peak1D F1="6.331342" intensity="4.456676e+000" type="0"/>
    <Peak1D F1="6.330160" intensity="4.133222e+000" type="0"/>
    <Peak1D F1="6.328781" intensity="4.395274e+000" type="0"/>
    <Peak1D F1="6.298182" intensity="8.958447e-003" type="0"/>
    <Peak1D F1="6.280638" intensity="6.942219e-003" type="0"/>
    <Peak1D F1="6.256796" intensity="3.712706e-003" type="0"/>
    <Peak1D F1="6.240035" intensity="5.714214e-003" type="0"/>
    <Peak1D F1="6.232703" intensity="2.748873e-003" type="0"/>
    <Peak1D F1="6.126222" intensity="2.363709e-002" type="0"/>
    <Peak1D F1="5.975853" intensity="1.017701e-002" type="0"/>
    <Peak1D F1="5.973545" intensity="1.020448e-002" type="0"/>
    <Peak1D F1="5.931828" intensity="9.076723e-003" type="0"/>
    <Peak1D F1="5.929521" intensity="9.066060e-003" type="0"/>
    <Peak1D F1="5.892941" intensity="1.892535e-002" type="0"/>
    <Peak1D F1="5.890182" intensity="2.033719e-002" type="0"/>
    <Peak1D F1="5.839372" intensity="3.492715e-003" type="0"/>
    <Peak1D F1="5.837321" intensity="3.806411e-003" type="0"/>
    <Peak1D F1="5.810584" intensity="4.789446e-003" type="0"/>
    <Peak1D F1="5.785060" intensity="2.026242e+000" type="0"/>
    <Peak1D F1="5.782747" intensity="2.025927e+000" type="0"/>
    <Peak1D F1="5.766656" intensity="1.183151e-002" type="0"/>
    <Peak1D F1="5.760817" intensity="1.014070e-002" type="0"/>
    <Peak1D F1="5.758492" intensity="7.891274e-003" type="0"/>
    <Peak1D F1="5.741062" intensity="1.879542e+000" type="0"/>
    <Peak1D F1="5.738747" intensity="1.854041e+000" type="0"/>
    <Peak1D F1="5.725097" intensity="2.061854e-002" type="0"/>
    <Peak1D F1="5.722264" intensity="2.099991e-002" type="0"/>
    <Peak1D F1="5.719250" intensity="1.699615e-002" type="0"/>
    <Peak1D F1="5.712224" intensity="4.458168e-002" type="0"/>
    <Peak1D F1="5.709241" intensity="6.336721e-002" type="0"/>
    <Peak1D F1="5.699428" intensity="1.699716e+000" type="0"/>
    <Peak1D F1="5.696670" intensity="4.380404e+000" type="0"/>
    <Peak1D F1="5.693832" intensity="4.329586e+000" type="0"/>
    <Peak1D F1="5.691090" intensity="1.636447e+000" type="0"/>
    <Peak1D F1="5.681039" intensity="6.369326e-002" type="0"/>
    <Peak1D F1="5.678095" intensity="5.269917e-002" type="0"/>
    <Peak1D F1="5.667052" intensity="8.497639e-003" type="0"/>
    <Peak1D F1="5.663729" intensity="8.350583e-003" type="0"/>
    <Peak1D F1="5.646252" intensity="7.240603e-003" type="0"/>
    <Peak1D F1="5.643516" intensity="6.392951e-003" type="0"/>
    <Peak1D F1="5.622003" intensity="3.383206e-003" type="0"/>
    <Peak1D F1="5.605598" intensity="2.444047e-003" type="0"/>
    <Peak1D F1="5.589937" intensity="1.231485e-002" type="0"/>
    <Peak1D F1="5.587677" intensity="1.126990e-002" type="0"/>
    <Peak1D F1="5.545931" intensity="9.860079e-003" type="0"/>
    <Peak1D F1="5.543665" intensity="9.294597e-003" type="0"/>
    <Peak1D F1="5.495827" intensity="2.080575e-002" type="0"/>
    <Peak1D F1="5.493047" intensity="1.870235e-002" type="0"/>
    <Peak1D F1="5.468230" intensity="1.139336e-002" type="0"/>
    <Peak1D F1="5.466002" intensity="9.995704e-003" type="0"/>
    <Peak1D F1="5.440861" intensity="9.384495e-003" type="0"/>
    <Peak1D F1="5.438748" intensity="9.629157e-003" type="0"/>
    <Peak1D F1="5.424320" intensity="2.784658e-003" type="0"/>
    <Peak1D F1="5.306017" intensity="2.087712e-003" type="0"/>
    <Peak1D F1="5.295629" intensity="7.116191e-003" type="0"/>
    <Peak1D F1="5.279974" intensity="4.041348e-001" type="0"/>
    <Peak1D F1="5.278748" intensity="4.391836e-001" type="0"/>
    <Peak1D F1="5.277479" intensity="4.289806e-001" type="0"/>
    <Peak1D F1="5.269945" intensity="1.850932e+000" type="0"/>
    <Peak1D F1="5.267718" intensity="1.817333e+000" type="0"/>
    <Peak1D F1="5.255005" intensity="4.349095e-002" type="0"/>
    <Peak1D F1="5.252670" intensity="3.972393e-002" type="0"/>
    <Peak1D F1="5.242741" intensity="1.783566e+000" type="0"/>
    <Peak1D F1="5.240500" intensity="1.776158e+000" type="0"/>
    <Peak1D F1="5.236076" intensity="4.225407e-001" type="0"/>
    <Peak1D F1="5.234789" intensity="4.264230e-001" type="0"/>
    <Peak1D F1="5.233522" intensity="3.945929e-001" type="0"/>
    <Peak1D F1="5.219979" intensity="1.508906e-002" type="0"/>
    <Peak1D F1="5.207556" intensity="5.920841e-003" type="0"/>
    <Peak1D F1="5.191910" intensity="4.220066e-002" type="0"/>
    <Peak1D F1="5.188428" intensity="8.793601e-002" type="0"/>
    <Peak1D F1="5.184899" intensity="1.133690e-001" type="0"/>
    <Peak1D F1="5.181376" intensity="9.344581e-002" type="0"/>
    <Peak1D F1="5.177864" intensity="6.649435e-002" type="0"/>
    <Peak1D F1="5.174760" intensity="9.491511e-002" type="0"/>
    <Peak1D F1="5.171325" intensity="1.761672e-001" type="0"/>
    <Peak1D F1="5.167875" intensity="2.283472e-001" type="0"/>
    <Peak1D F1="5.164375" intensity="1.923788e-001" type="0"/>
    <Peak1D F1="5.160794" intensity="1.184931e-001" type="0"/>
    <Peak1D F1="5.157561" intensity="9.094552e-002" type="0"/>
    <Peak1D F1="5.154312" intensity="1.097573e-001" type="0"/>
    <Peak1D F1="5.150835" intensity="1.091055e-001" type="0"/>
    <Peak1D F1="5.147278" intensity="7.304060e-002" type="0"/>
    <Peak1D F1="5.126277" intensity="4.521349e-003" type="0"/>
    <Peak1D F1="5.123180" intensity="4.569245e-003" type="0"/>
    <Peak1D F1="5.119658" intensity="4.574453e-003" type="0"/>
    <Peak1D F1="5.110076" intensity="1.336645e-002" type="0"/>
    <Peak1D F1="5.082074" intensity="3.410807e-001" type="0"/>
    <Peak1D F1="5.080440" intensity="3.535404e-001" type="0"/>
    <Peak1D F1="5.077584" intensity="1.876599e-001" type="0"/>
    <Peak1D F1="5.067839" intensity="2.851306e-002" type="0"/>
    <Peak1D F1="5.065347" intensity="2.300406e-002" type="0"/>
    <Peak1D F1="5.055064" intensity="3.126113e-001" type="0"/>
    <Peak1D F1="5.053402" intensity="3.399399e-001" type="0"/>
    <Peak1D F1="5.050515" intensity="1.873927e-001" type="0"/>
    <Peak1D F1="5.045646" intensity="4.534629e-002" type="0"/>
    <Peak1D F1="5.043612" intensity="5.109970e-002" type="0"/>
    <Peak1D F1="5.040154" intensity="5.613796e-002" type="0"/>
    <Peak1D F1="5.027708" intensity="5.758361e-001" type="0"/>
    <Peak1D F1="5.013063" intensity="4.262113e-001" type="0"/>
    <Peak1D F1="5.010428" intensity="4.694628e-001" type="0"/>
    <Peak1D F1="4.977160" intensity="4.055720e-003" type="0"/>
    <Peak1D F1="4.956613" intensity="2.183617e-003" type="0"/>
    <Peak1D F1="4.932665" intensity="4.611792e-003" type="0"/>
    <Peak1D F1="4.929017" intensity="1.606516e-002" type="0"/>
    <Peak1D F1="4.925380" intensity="2.333348e-002" type="0"/>
    <Peak1D F1="4.921752" intensity="1.547797e-002" type="0"/>
    <Peak1D F1="4.918190" intensity="4.278117e-003" type="0"/>
    <Peak1D F1="4.852339" intensity="3.129317e-003" type="0"/>
    <Peak1D F1="4.847130" intensity="2.436617e-003" type="0"/>
    <Peak1D F1="4.829425" intensity="2.485084e-003" type="0"/>
    <Peak1D F1="4.811691" intensity="3.788767e-003" type="0"/>
    <Peak1D F1="4.772129" intensity="2.225520e-003" type="0"/>
    <Peak1D F1="4.717952" intensity="8.558436e-003" type="0"/>
    <Peak1D F1="4.699205" intensity="6.122387e-002" type="0"/>
    <Peak1D F1="4.697198" intensity="7.386603e-002" type="0"/>
    <Peak1D F1="4.694762" intensity="6.099667e-002" type="0"/>
    <Peak1D F1="4.678036" intensity="2.451492e-003" type="0"/>
    <Peak1D F1="4.633764" intensity="4.412181e-002" type="0"/>
    <Peak1D F1="4.629560" intensity="8.431181e-002" type="0"/>
    <Peak1D F1="4.625335" intensity="4.296745e-002" type="0"/>
    <Peak1D F1="4.434999" intensity="5.931012e-003" type="0"/>
    <Peak1D F1="4.419507" intensity="7.369181e-003" type="0"/>
    <Peak1D F1="4.414948" intensity="6.279062e-003" type="0"/>
    <Peak1D F1="4.399192" intensity="5.990110e-003" type="0"/>
    <Peak1D F1="4.374279" intensity="1.979044e-002" type="0"/>
    <Peak1D F1="4.357771" intensity="4.321698e-002" type="0"/>
    <Peak1D F1="4.341241" intensity="2.045066e-002" type="0"/>
    <Peak1D F1="4.306209" intensity="1.787235e-002" type="0"/>
    <Peak1D F1="4.289526" intensity="4.958974e-002" type="0"/>
    <Peak1D F1="4.273023" intensity="3.887099e-002" type="0"/>
    <Peak1D F1="4.256863" intensity="1.020469e-002" type="0"/>
    <Peak1D F1="4.240780" intensity="2.406661e-003" type="0"/>
    <Peak1D F1="4.235626" intensity="4.950512e-003" type="0"/>
    <Peak1D F1="4.228073" intensity="4.742761e-003" type="0"/>
    <Peak1D F1="4.219355" intensity="2.263959e-002" type="0"/>
    <Peak1D F1="4.208644" intensity="3.231970e-002" type="0"/>
    <Peak1D F1="4.202447" intensity="7.632888e-002" type="0"/>
    <Peak1D F1="4.193515" intensity="4.305758e+000" type="0"/>
    <Peak1D F1="4.176985" intensity="8.812560e+000" type="0"/>
    <Peak1D F1="4.160429" intensity="4.369408e+000" type="0"/>
    <Peak1D F1="4.147093" intensity="3.728340e-002" type="0"/>
    <Peak1D F1="4.125634" intensity="3.984687e+000" type="0"/>
    <Peak1D F1="4.108961" intensity="8.146082e+000" type="0"/>
    <Peak1D F1="4.092260" intensity="4.057785e+000" type="0"/>
    <Peak1D F1="4.079678" intensity="3.525154e-002" type="0"/>
    <Peak1D F1="4.075738" intensity="3.325538e-002" type="0"/>
    <Peak1D F1="4.069414" intensity="2.028550e-002" type="0"/>
    <Peak1D F1="4.058661" intensity="1.332880e-002" type="0"/>
    <Peak1D F1="4.039372" intensity="6.156906e-003" type="0"/>
    <Peak1D F1="4.014757" intensity="6.553389e-003" type="0"/>
    <Peak1D F1="4.007425" intensity="2.440440e-002" type="0"/>
    <Peak1D F1="3.997734" intensity="6.135211e-003" type="0"/>
    <Peak1D F1="3.990882" intensity="4.656690e-002" type="0"/>
    <Peak1D F1="3.974304" intensity="2.273558e-002" type="0"/>
    <Peak1D F1="3.968680" intensity="6.527053e-003" type="0"/>
    <Peak1D F1="3.952332" intensity="5.932610e-003" type="0"/>
    <Peak1D F1="3.939779" intensity="2.077542e-002" type="0"/>
    <Peak1D F1="3.923071" intensity="4.145116e-002" type="0"/>
    <Peak1D F1="3.906382" intensity="2.065000e-002" type="0"/>
    <Peak1D F1="3.898874" intensity="4.811692e-003" type="0"/>
    <Peak1D F1="3.882244" intensity="3.716811e-003" type="0"/>
    <Peak1D F1="3.675766" intensity="3.225275e-002" type="0"/>
    <Peak1D F1="3.659327" intensity="6.568486e-002" type="0"/>
    <Peak1D F1="3.642841" intensity="3.204225e-002" type="0"/>
    <Peak1D F1="3.634290" intensity="2.738644e-003" type="0"/>
    <Peak1D F1="3.623524" intensity="2.808609e-003" type="0"/>
    <Peak1D F1="3.620743" intensity="2.743535e-003" type="0"/>
    <Peak1D F1="3.607925" intensity="2.181863e-003" type="0"/>
    <Peak1D F1="3.506741" intensity="4.279226e-002" type="0"/>
    <Peak1D F1="3.504743" intensity="4.255306e-002" type="0"/>
    <Peak1D F1="3.491476" intensity="7.435453e-003" type="0"/>
    <Peak1D F1="3.414269" intensity="4.419255e-003" type="0"/>
    <Peak1D F1="3.409911" intensity="3.600090e-003" type="0"/>
    <Peak1D F1="3.400761" intensity="5.655968e-003" type="0"/>
    <Peak1D F1="3.379802" intensity="3.883119e-002" type="0"/>
    <Peak1D F1="3.377677" intensity="3.886755e-002" type="0"/>
    <Peak1D F1="3.372252" intensity="3.116062e-002" type="0"/>
    <Peak1D F1="3.346049" intensity="8.556423e+000" type="0"/>
    <Peak1D F1="3.343894" intensity="8.410402e+000" type="0"/>
    <Peak1D F1="3.313351" intensity="1.715385e-002" type="0"/>
    <Peak1D F1="3.295773" intensity="1.190368e-002" type="0"/>
    <Peak1D F1="3.271948" intensity="5.674346e-003" type="0"/>
    <Peak1D F1="3.181673" intensity="4.388653e-002" type="0"/>
    <Peak1D F1="3.179705" intensity="4.277576e-002" type="0"/>
    <Peak1D F1="3.133908" intensity="7.997944e-002" type="0"/>
    <Peak1D F1="3.065402" intensity="6.651411e-002" type="0"/>
    <Peak1D F1="3.064244" intensity="6.752581e-002" type="0"/>
    <Peak1D F1="3.028511" intensity="5.682147e-003" type="0"/>
    <Peak1D F1="3.021955" intensity="2.929419e-003" type="0"/>
    <Peak1D F1="3.015089" intensity="3.127799e-003" type="0"/>
    <Peak1D F1="3.006968" intensity="9.314192e-003" type="0"/>
    <Peak1D F1="3.000231" intensity="8.161846e-003" type="0"/>
    <Peak1D F1="2.990566" intensity="4.013975e-002" type="0"/>
    <Peak1D F1="2.964220" intensity="1.500000e+001" type="0"/>
    <Peak1D F1="2.943527" intensity="4.223929e-002" type="0"/>
    <Peak1D F1="2.941012" intensity="4.964533e-002" type="0"/>
    <Peak1D F1="2.934039" intensity="2.246854e-002" type="0"/>
    <Peak1D F1="2.930846" intensity="2.204954e-002" type="0"/>
    <Peak1D F1="2.920568" intensity="4.202611e-002" type="0"/>
    <Peak1D F1="2.894747" intensity="1.266753e+001" type="0"/>
    <Peak1D F1="2.893546" intensity="1.272737e+001" type="0"/>
    <Peak1D F1="2.872863" intensity="4.534335e-002" type="0"/>
    <Peak1D F1="2.871070" intensity="5.131054e-002" type="0"/>
    <Peak1D F1="2.863766" intensity="1.831199e-002" type="0"/>
    <Peak1D F1="2.843079" intensity="1.440443e-002" type="0"/>
    <Peak1D F1="2.833402" intensity="5.535017e-003" type="0"/>
    <Peak1D F1="2.820659" intensity="7.813398e-003" type="0"/>
    <Peak1D F1="2.807684" intensity="4.621003e-003" type="0"/>
    <Peak1D F1="2.790207" intensity="8.318743e-002" type="0"/>
    <Peak1D F1="2.772549" intensity="2.253702e-003" type="0"/>
    <Peak1D F1="2.766000" intensity="4.031017e-003" type="0"/>
    <Peak1D F1="2.730561" intensity="3.848836e-003" type="0"/>
    <Peak1D F1="2.719721" intensity="6.788988e-002" type="0"/>
    <Peak1D F1="2.718561" intensity="6.906144e-002" type="0"/>
    <Peak1D F1="2.713140" intensity="8.170197e-003" type="0"/>
    <Peak1D F1="2.695428" intensity="3.712547e-003" type="0"/>
    <Peak1D F1="2.633519" intensity="1.823832e-002" type="0"/>
    <Peak1D F1="2.611829" intensity="3.166606e-003" type="0"/>
    <Peak1D F1="2.597996" intensity="2.838388e-003" type="0"/>
    <Peak1D F1="2.423978" intensity="6.795311e-003" type="0"/>
    <Peak1D F1="2.418803" intensity="2.569441e-003" type="0"/>
    <Peak1D F1="2.406793" intensity="4.578179e-003" type="0"/>
    <Peak1D F1="2.392391" intensity="5.997956e-003" type="0"/>
    <Peak1D F1="2.375230" intensity="2.089014e-002" type="0"/>
    <Peak1D F1="2.370445" intensity="1.621243e-002" type="0"/>
    <Peak1D F1="2.346917" intensity="1.645774e-002" type="0"/>
    <Peak1D F1="2.341852" intensity="2.514624e-002" type="0"/>
    <Peak1D F1="2.336709" intensity="1.675911e-002" type="0"/>
    <Peak1D F1="2.319716" intensity="2.656747e-003" type="0"/>
    <Peak1D F1="2.309597" intensity="4.187470e-003" type="0"/>
    <Peak1D F1="2.302633" intensity="7.141386e-003" type="0"/>
    <Peak1D F1="2.298685" intensity="7.650415e-003" type="0"/>
    <Peak1D F1="2.293453" intensity="5.207856e-003" type="0"/>
    <Peak1D F1="2.290823" intensity="5.621667e-003" type="0"/>
    <Peak1D F1="2.283712" intensity="4.869874e-003" type="0"/>
    <Peak1D F1="2.265925" intensity="7.417552e-002" type="0"/>
    <Peak1D F1="2.255344" intensity="1.231099e-001" type="0"/>
    <Peak1D F1="2.241700" intensity="2.773848e-001" type="0"/>
    <Peak1D F1="2.236285" intensity="2.928896e-001" type="0"/>
    <Peak1D F1="2.233342" intensity="2.567857e-001" type="0"/>
    <Peak1D F1="2.224475" intensity="6.449090e-001" type="0"/>
    <Peak1D F1="2.214744" intensity="3.199665e-001" type="0"/>
    <Peak1D F1="2.199966" intensity="3.389407e-001" type="0"/>
    <Peak1D F1="2.184559" intensity="1.809083e-001" type="0"/>
    <Peak1D F1="2.165542" intensity="5.130966e-002" type="0"/>
    <Peak1D F1="2.162628" intensity="4.943217e-002" type="0"/>
    <Peak1D F1="2.160289" intensity="4.672374e-002" type="0"/>
    <Peak1D F1="2.115790" intensity="1.464410e-002" type="0"/>
    <Peak1D F1="2.109730" intensity="1.385390e-002" type="0"/>
    <Peak1D F1="2.101936" intensity="1.332068e-002" type="0"/>
    <Peak1D F1="2.086215" intensity="2.647961e-002" type="0"/>
    <Peak1D F1="2.080736" intensity="3.114809e-002" type="0"/>
    <Peak1D F1="2.065231" intensity="1.834028e-002" type="0"/>
    <Peak1D F1="2.057575" intensity="2.769811e-002" type="0"/>
    <Peak1D F1="2.046739" intensity="2.185564e-002" type="0"/>
    <Peak1D F1="2.044020" intensity="1.865446e-002" type="0"/>
    <Peak1D F1="2.037252" intensity="1.500528e-002" type="0"/>
    <Peak1D F1="2.032103" intensity="1.236517e-002" type="0"/>
    <Peak1D F1="2.023126" intensity="1.693105e-002" type="0"/>
    <Peak1D F1="2.016373" intensity="2.176241e-002" type="0"/>
    <Peak1D F1="2.011662" intensity="2.436657e-002" type="0"/>
    <Peak1D F1="2.008477" intensity="2.909605e-002" type="0"/>
    <Peak1D F1="2.004504" intensity="2.489657e-002" type="0"/>
    <Peak1D F1="2.000629" intensity="1.526904e-002" type="0"/>
    <Peak1D F1="1.997113" intensity="1.080338e-002" type="0"/>
    <Peak1D F1="1.992586" intensity="1.577306e-002" type="0"/>
    <Peak1D F1="1.981337" intensity="1.268909e-002" type="0"/>
    <Peak1D F1="1.976850" intensity="1.476956e-002" type="0"/>
    <Peak1D F1="1.973498" intensity="1.251104e-002" type="0"/>
    <Peak1D F1="1.965608" intensity="1.021822e-002" type="0"/>
    <Peak1D F1="1.957629" intensity="1.279608e-002" type="0"/>
    <Peak1D F1="1.953080" intensity="1.164456e-002" type="0"/>
    <Peak1D F1="1.898779" intensity="7.587264e-002" type="0"/>
    <Peak1D F1="1.863719" intensity="1.043535e-001" type="0"/>
    <Peak1D F1="1.844666" intensity="1.285117e-001" type="0"/>
    <Peak1D F1="1.838949" intensity="1.801710e-001" type="0"/>
    <Peak1D F1="1.836992" intensity="1.925976e-001" type="0"/>
    <Peak1D F1="1.835591" intensity="1.866912e-001" type="0"/>
    <Peak1D F1="1.833572" intensity="1.671474e-001" type="0"/>
    <Peak1D F1="1.821197" intensity="9.846275e-002" type="0"/>
    <Peak1D F1="1.799528" intensity="7.759656e-002" type="0"/>
    <Peak1D F1="1.793824" intensity="7.335755e-002" type="0"/>
    <Peak1D F1="1.786739" intensity="6.091760e-002" type="0"/>
    <Peak1D F1="1.778074" intensity="7.551459e-002" type="0"/>
    <Peak1D F1="1.761764" intensity="7.016765e-002" type="0"/>
    <Peak1D F1="1.755289" intensity="6.530153e-002" type="0"/>
    <Peak1D F1="1.736068" intensity="1.165065e+001" type="0"/>
    <Peak1D F1="1.729721" intensity="4.650488e-001" type="0"/>
    <Peak1D F1="1.712504" intensity="1.728396e+000" type="0"/>
    <Peak1D F1="1.710039" intensity="1.663303e+000" type="0"/>
    <Peak1D F1="1.698008" intensity="8.213627e-001" type="0"/>
    <Peak1D F1="1.681696" intensity="2.077801e+000" type="0"/>
    <Peak1D F1="1.680641" intensity="2.075031e+000" type="0"/>
    <Peak1D F1="1.674010" intensity="7.131782e-001" type="0"/>
    <Peak1D F1="1.665352" intensity="2.180147e+000" type="0"/>
    <Peak1D F1="1.663380" intensity="2.650031e+000" type="0"/>
    <Peak1D F1="1.660443" intensity="1.620373e+000" type="0"/>
    <Peak1D F1="1.657452" intensity="1.600649e+000" type="0"/>
    <Peak1D F1="1.643619" intensity="2.473159e+000" type="0"/>
    <Peak1D F1="1.638807" intensity="2.304101e+000" type="0"/>
    <Peak1D F1="1.637440" intensity="2.297232e+000" type="0"/>
    <Peak1D F1="1.626494" intensity="2.983910e+000" type="0"/>
    <Peak1D F1="1.622484" intensity="3.570858e+000" type="0"/>
    <Peak1D F1="1.620568" intensity="3.217701e+000" type="0"/>
    <Peak1D F1="1.614385" intensity="1.503905e+000" type="0"/>
    <Peak1D F1="1.600596" intensity="2.293506e+000" type="0"/>
    <Peak1D F1="1.583861" intensity="1.042377e+000" type="0"/>
    <Peak1D F1="1.569613" intensity="8.601064e-002" type="0"/>
    <Peak1D F1="1.562245" intensity="3.396684e-002" type="0"/>
    <Peak1D F1="1.556297" intensity="4.199814e-002" type="0"/>
    <Peak1D F1="1.552113" intensity="5.016603e-002" type="0"/>
    <Peak1D F1="1.544662" intensity="2.803233e-002" type="0"/>
    <Peak1D F1="1.539487" intensity="2.061322e-002" type="0"/>
    <Peak1D F1="1.534525" intensity="2.375626e-002" type="0"/>
    <Peak1D F1="1.524783" intensity="2.430918e-002" type="0"/>
    <Peak1D F1="1.506741" intensity="2.419453e-002" type="0"/>
    <Peak1D F1="1.498006" intensity="1.577802e-002" type="0"/>
    <Peak1D F1="1.492168" intensity="2.171580e-002" type="0"/>
    <Peak1D F1="1.487366" intensity="2.154433e-002" type="0"/>
    <Peak1D F1="1.485355" intensity="1.993912e-002" type="0"/>
    <Peak1D F1="1.461648" intensity="5.485491e-001" type="0"/>
    <Peak1D F1="1.454794" intensity="7.446785e-002" type="0"/>
    <Peak1D F1="1.443064" intensity="1.744316e+000" type="0"/>
    <Peak1D F1="1.429264" intensity="1.429016e+000" type="0"/>
    <Peak1D F1="1.424070" intensity="2.568718e+000" type="0"/>
    <Peak1D F1="1.410858" intensity="2.636167e+000" type="0"/>
    <Peak1D F1="1.405160" intensity="2.818009e+000" type="0"/>
    <Peak1D F1="1.396833" intensity="1.132449e+000" type="0"/>
    <Peak1D F1="1.392043" intensity="2.906347e+000" type="0"/>
    <Peak1D F1="1.387099" intensity="2.110128e+000" type="0"/>
    <Peak1D F1="1.378378" intensity="1.070215e+000" type="0"/>
    <Peak1D F1="1.373077" intensity="2.642524e+000" type="0"/>
    <Peak1D F1="1.360080" intensity="4.577603e-001" type="0"/>
    <Peak1D F1="1.354829" intensity="1.661154e+000" type="0"/>
    <Peak1D F1="1.336577" intensity="5.078480e-001" type="0"/>
    <Peak1D F1="1.319944" intensity="3.083748e-002" type="0"/>
    <Peak1D F1="1.310230" intensity="2.416484e-002" type="0"/>
    <Peak1D F1="1.288267" intensity="2.415664e-002" type="0"/>
    <Peak1D F1="1.284603" intensity="2.315242e-002" type="0"/>
    <Peak1D F1="1.278929" intensity="2.478723e-002" type="0"/>
    <Peak1D F1="1.270965" intensity="2.641471e-002" type="0"/>
    <Peak1D F1="1.265622" intensity="2.172842e-002" type="0"/>
    <Peak1D F1="1.257409" intensity="1.535299e-002" type="0"/>
    <Peak1D F1="1.251685" intensity="1.892630e-002" type="0"/>
    <Peak1D F1="1.246831" intensity="2.358451e-002" type="0"/>
    <Peak1D F1="1.240177" intensity="9.475292e-003" type="0"/>
    <Peak1D F1="1.233144" intensity="1.960645e-002" type="0"/>
    <Peak1D F1="1.228024" intensity="1.530105e-002" type="0"/>
    <Peak1D F1="1.214433" intensity="1.669001e-002" type="0"/>
    <Peak1D F1="1.205265" intensity="6.012470e-003" type="0"/>
    <Peak1D F1="1.196036" intensity="1.103636e-002" type="0"/>
    <Peak1D F1="1.186454" intensity="3.972548e-003" type="0"/>
    <Peak1D F1="1.178080" intensity="4.783156e-003" type="0"/>
    <Peak1D F1="1.169586" intensity="2.827421e-003" type="0"/>
    <Peak1D F1="1.153893" intensity="9.718317e-003" type="0"/>
    <Peak1D F1="1.128740" intensity="3.414804e-002" type="0"/>
    <Peak1D F1="1.113252" intensity="4.275835e-002" type="0"/>
    <Peak1D F1="1.110463" intensity="7.290629e-002" type="0"/>
    <Peak1D F1="1.095137" intensity="7.114493e-002" type="0"/>
    <Peak1D F1="1.076753" intensity="2.502452e-002" type="0"/>
    <Peak1D F1="1.060392" intensity="5.325749e-003" type="0"/>
    <Peak1D F1="1.046716" intensity="1.074446e-002" type="0"/>
    <Peak1D F1="1.038552" intensity="4.600730e-002" type="0"/>
    <Peak1D F1="1.032404" intensity="1.168085e-002" type="0"/>
    <Peak1D F1="1.029806" intensity="1.272817e-002" type="0"/>
    <Peak1D F1="1.025130" intensity="9.327916e-003" type="0"/>
    <Peak1D F1="1.020144" intensity="1.149182e-002" type="0"/>
    <Peak1D F1="1.014098" intensity="8.818537e-003" type="0"/>
    <Peak1D F1="1.010100" intensity="1.137044e-002" type="0"/>
    <Peak1D F1="1.000599" intensity="3.299590e-002" type="0"/>
    <Peak1D F1="0.994188" intensity="4.103847e-002" type="0"/>
    <Peak1D F1="0.974491" intensity="6.787665e+000" type="0"/>
    <Peak1D F1="0.959143" intensity="8.021656e+000" type="0"/>
    <Peak1D F1="0.956087" intensity="1.439452e+001" type="0"/>
    <Peak1D F1="0.940827" intensity="1.435716e+001" type="0"/>
    <Peak1D F1="0.937742" intensity="6.772729e+000" type="0"/>
    <Peak1D F1="0.922384" intensity="5.624567e+000" type="0"/>
    <Peak1D F1="0.908438" intensity="6.261368e-002" type="0"/>
    <Peak1D F1="0.899879" intensity="3.800014e-002" type="0"/>
    <Peak1D F1="0.893408" intensity="2.639015e-002" type="0"/>
    <Peak1D F1="0.889761" intensity="2.964489e-002" type="0"/>
    <Peak1D F1="0.881363" intensity="1.821416e-002" type="0"/>
    <Peak1D F1="0.874444" intensity="1.439965e-002" type="0"/>
    <Peak1D F1="0.869528" intensity="1.834993e-002" type="0"/>
    <Peak1D F1="0.849135" intensity="1.049871e-002" type="0"/>
    <Peak1D F1="0.840879" intensity="8.991801e-003" type="0"/>
    <Peak1D F1="0.830451" intensity="2.559062e-002" type="0"/>
    <Peak1D F1="0.816474" intensity="4.398484e-002" type="0"/>
    <Peak1D F1="0.812624" intensity="2.686289e-002" type="0"/>
    <Peak1D F1="0.801162" intensity="4.870720e-002" type="0"/>
    <Peak1D F1="0.798060" intensity="8.383791e-002" type="0"/>
    <Peak1D F1="0.782805" intensity="8.426805e-002" type="0"/>
    <Peak1D F1="0.779646" intensity="4.633550e-002" type="0"/>
    <Peak1D F1="0.776122" intensity="5.442980e-002" type="0"/>
    <Peak1D F1="0.764403" intensity="3.660610e-002" type="0"/>
    <Peak1D F1="0.748568" intensity="4.865145e-003" type="0"/>
    <Peak1D F1="0.727961" intensity="5.460618e-003" type="0"/>
    <Peak1D F1="0.705364" intensity="5.178643e-003" type="0"/>
    <Peak1D F1="0.689867" intensity="3.526632e-003" type="0"/>
    <Peak1D F1="0.670983" intensity="3.304128e-003" type="0"/>
    <Peak1D F1="0.647106" intensity="4.713750e-003" type="0"/>
    <Peak1D F1="0.627423" intensity="4.615147e-003" type="0"/>
    <Peak1D F1="0.604947" intensity="2.990394e-003" type="0"/>
    <Peak1D F1="0.109364" intensity="7.808946e-003" type="0"/>
  </PeakList1D>
</PeakList>
