<?xml version="1.0" encoding="UTF-8"?>
<PeakList>
  <PeakList1D>
    <PeakList1DHeader creator="NMR User1" date="2022-11-18T12:35:58.081+08:00" expNo="10" name="TP40" owner="" procNo="1" source="C:/Bruker/TopSpin3.2/data/May 2014/2-Balamurugan">
      <PeakPickDetails>F1=15.472890ppm, F2=-1.503590ppm, MI=0.00cm, MAXI=10000.00cm, PC=1.000
      </PeakPickDetails>
    </PeakList1DHeader>
    <Peak1D F1="8.247439" intensity="8.583320e-003" type="0"/>
    <Peak1D F1="8.148665" intensity="9.897866e-004" type="0"/>
    <Peak1D F1="8.140641" intensity="1.167221e-003" type="0"/>
    <Peak1D F1="8.126856" intensity="1.257190e-003" type="0"/>
    <Peak1D F1="8.113734" intensity="1.853341e-003" type="0"/>
    <Peak1D F1="8.095235" intensity="2.547676e-003" type="0"/>
    <Peak1D F1="8.010624" intensity="1.581501e+000" type="0"/>
    <Peak1D F1="7.768125" intensity="8.715488e-003" type="0"/>
    <Peak1D F1="7.611495" intensity="9.376653e-003" type="0"/>
    <Peak1D F1="7.595706" intensity="8.458596e-003" type="0"/>
    <Peak1D F1="7.590819" intensity="1.517233e-002" type="0"/>
    <Peak1D F1="7.573797" intensity="1.074608e-003" type="0"/>
    <Peak1D F1="7.539294" intensity="4.834444e-003" type="0"/>
    <Peak1D F1="7.535827" intensity="8.118349e-003" type="0"/>
    <Peak1D F1="7.531281" intensity="3.401483e-003" type="0"/>
    <Peak1D F1="7.526707" intensity="1.130378e-002" type="0"/>
    <Peak1D F1="7.521165" intensity="9.788607e-003" type="0"/>
    <Peak1D F1="7.517851" intensity="1.649061e-002" type="0"/>
    <Peak1D F1="7.514292" intensity="1.031003e-002" type="0"/>
    <Peak1D F1="7.500082" intensity="1.140214e-002" type="0"/>
    <Peak1D F1="7.496253" intensity="9.827791e-003" type="0"/>
    <Peak1D F1="7.465000" intensity="6.444731e-003" type="0"/>
    <Peak1D F1="7.447052" intensity="1.656052e-002" type="0"/>
    <Peak1D F1="7.442273" intensity="1.230040e-002" type="0"/>
    <Peak1D F1="7.419866" intensity="1.468177e+000" type="0"/>
    <Peak1D F1="7.415866" intensity="2.058561e+000" type="0"/>
    <Peak1D F1="7.411158" intensity="5.928345e-001" type="0"/>
    <Peak1D F1="7.397977" intensity="2.918616e+000" type="0"/>
    <Peak1D F1="7.396394" intensity="2.598895e+000" type="0"/>
    <Peak1D F1="7.390903" intensity="3.731939e-001" type="0"/>
    <Peak1D F1="7.366571" intensity="1.137413e-002" type="0"/>
    <Peak1D F1="7.340622" intensity="1.061026e+000" type="0"/>
    <Peak1D F1="7.338296" intensity="1.651117e+000" type="0"/>
    <Peak1D F1="7.333804" intensity="5.459483e-001" type="0"/>
    <Peak1D F1="7.320461" intensity="3.303763e+000" type="0"/>
    <Peak1D F1="7.316693" intensity="1.409110e+000" type="0"/>
    <Peak1D F1="7.304816" intensity="8.559126e-001" type="0"/>
    <Peak1D F1="7.301316" intensity="1.705271e+000" type="0"/>
    <Peak1D F1="7.296458" intensity="2.680784e-001" type="0"/>
    <Peak1D F1="7.267620" intensity="2.295434e+000" type="0"/>
    <Peak1D F1="7.263464" intensity="1.310936e+000" type="0"/>
    <Peak1D F1="7.260048" intensity="6.784329e-001" type="0"/>
    <Peak1D F1="7.250892" intensity="4.778670e-001" type="0"/>
    <Peak1D F1="7.245330" intensity="1.502792e+000" type="0"/>
    <Peak1D F1="7.239381" intensity="3.340040e-001" type="0"/>
    <Peak1D F1="7.230452" intensity="2.898189e-001" type="0"/>
    <Peak1D F1="7.227184" intensity="4.830782e-001" type="0"/>
    <Peak1D F1="7.223906" intensity="2.431863e-001" type="0"/>
    <Peak1D F1="7.196743" intensity="1.121284e-002" type="0"/>
    <Peak1D F1="7.192498" intensity="6.149929e-003" type="0"/>
    <Peak1D F1="7.168635" intensity="9.616886e-004" type="0"/>
    <Peak1D F1="7.136358" intensity="1.120298e-002" type="0"/>
    <Peak1D F1="7.129485" intensity="2.485936e-003" type="0"/>
    <Peak1D F1="7.121022" intensity="1.152955e-002" type="0"/>
    <Peak1D F1="7.118587" intensity="1.263979e-002" type="0"/>
    <Peak1D F1="7.115120" intensity="9.417969e-003" type="0"/>
    <Peak1D F1="7.102802" intensity="5.274408e-003" type="0"/>
    <Peak1D F1="7.096768" intensity="6.107267e-003" type="0"/>
    <Peak1D F1="7.063646" intensity="4.456415e-003" type="0"/>
    <Peak1D F1="7.060362" intensity="2.604241e-003" type="0"/>
    <Peak1D F1="7.045370" intensity="8.178884e-003" type="0"/>
    <Peak1D F1="7.030484" intensity="1.626577e-003" type="0"/>
    <Peak1D F1="7.027005" intensity="3.442516e-003" type="0"/>
    <Peak1D F1="7.023702" intensity="1.699893e-003" type="0"/>
    <Peak1D F1="7.003548" intensity="9.253392e-003" type="0"/>
    <Peak1D F1="6.944516" intensity="5.432367e-003" type="0"/>
    <Peak1D F1="6.917267" intensity="5.316121e-003" type="0"/>
    <Peak1D F1="6.900480" intensity="5.833020e-003" type="0"/>
    <Peak1D F1="6.873370" intensity="5.770259e-003" type="0"/>
    <Peak1D F1="6.865769" intensity="1.687329e-003" type="0"/>
    <Peak1D F1="6.843373" intensity="7.214246e-003" type="0"/>
    <Peak1D F1="6.788444" intensity="1.453011e-003" type="0"/>
    <Peak1D F1="6.781048" intensity="2.684858e-003" type="0"/>
    <Peak1D F1="6.754150" intensity="1.004832e+000" type="0"/>
    <Peak1D F1="6.726943" intensity="1.047403e+000" type="0"/>
    <Peak1D F1="6.710149" intensity="1.108008e+000" type="0"/>
    <Peak1D F1="6.682941" intensity="1.137355e+000" type="0"/>
    <Peak1D F1="6.599357" intensity="1.330651e-003" type="0"/>
    <Peak1D F1="6.571917" intensity="1.457001e-003" type="0"/>
    <Peak1D F1="6.559731" intensity="5.126253e-003" type="0"/>
    <Peak1D F1="6.532350" intensity="5.599522e-003" type="0"/>
    <Peak1D F1="6.515627" intensity="2.451415e-002" type="0"/>
    <Peak1D F1="6.488470" intensity="5.837712e-003" type="0"/>
    <Peak1D F1="6.437885" intensity="1.004841e-003" type="0"/>
    <Peak1D F1="6.410635" intensity="3.102641e-001" type="0"/>
    <Peak1D F1="6.383593" intensity="3.273615e-001" type="0"/>
    <Peak1D F1="6.366619" intensity="3.440457e-001" type="0"/>
    <Peak1D F1="6.339594" intensity="3.575194e-001" type="0"/>
    <Peak1D F1="6.315193" intensity="3.860959e+000" type="0"/>
    <Peak1D F1="6.312888" intensity="3.652151e+000" type="0"/>
    <Peak1D F1="6.292389" intensity="1.501248e-002" type="0"/>
    <Peak1D F1="6.281785" intensity="4.210326e-003" type="0"/>
    <Peak1D F1="6.266584" intensity="3.457542e-003" type="0"/>
    <Peak1D F1="6.223358" intensity="2.901162e-003" type="0"/>
    <Peak1D F1="6.217729" intensity="1.616706e-003" type="0"/>
    <Peak1D F1="6.190318" intensity="1.203817e-003" type="0"/>
    <Peak1D F1="6.172811" intensity="1.036228e-003" type="0"/>
    <Peak1D F1="6.145594" intensity="1.348946e-003" type="0"/>
    <Peak1D F1="6.110109" intensity="1.970495e-002" type="0"/>
    <Peak1D F1="5.959500" intensity="1.082554e-002" type="0"/>
    <Peak1D F1="5.957271" intensity="1.050780e-002" type="0"/>
    <Peak1D F1="5.915483" intensity="9.814071e-003" type="0"/>
    <Peak1D F1="5.913227" intensity="9.660495e-003" type="0"/>
    <Peak1D F1="5.876478" intensity="1.644197e-002" type="0"/>
    <Peak1D F1="5.873748" intensity="1.715043e-002" type="0"/>
    <Peak1D F1="5.819653" intensity="4.593599e-003" type="0"/>
    <Peak1D F1="5.803088" intensity="2.401049e-003" type="0"/>
    <Peak1D F1="5.794866" intensity="6.178049e-003" type="0"/>
    <Peak1D F1="5.768758" intensity="2.146835e+000" type="0"/>
    <Peak1D F1="5.766489" intensity="2.067045e+000" type="0"/>
    <Peak1D F1="5.743044" intensity="1.146519e-002" type="0"/>
    <Peak1D F1="5.724755" intensity="1.978992e+000" type="0"/>
    <Peak1D F1="5.722485" intensity="1.890431e+000" type="0"/>
    <Peak1D F1="5.709167" intensity="2.154217e-002" type="0"/>
    <Peak1D F1="5.705916" intensity="1.783349e-002" type="0"/>
    <Peak1D F1="5.698604" intensity="2.611684e-002" type="0"/>
    <Peak1D F1="5.695618" intensity="4.008080e-002" type="0"/>
    <Peak1D F1="5.682812" intensity="1.493242e+000" type="0"/>
    <Peak1D F1="5.680151" intensity="3.631400e+000" type="0"/>
    <Peak1D F1="5.677341" intensity="3.522900e+000" type="0"/>
    <Peak1D F1="5.674672" intensity="1.327373e+000" type="0"/>
    <Peak1D F1="5.664578" intensity="5.378763e-002" type="0"/>
    <Peak1D F1="5.661597" intensity="4.085492e-002" type="0"/>
    <Peak1D F1="5.650280" intensity="5.391687e-003" type="0"/>
    <Peak1D F1="5.647235" intensity="4.770560e-003" type="0"/>
    <Peak1D F1="5.632649" intensity="3.637962e-003" type="0"/>
    <Peak1D F1="5.605402" intensity="9.569906e-004" type="0"/>
    <Peak1D F1="5.573626" intensity="1.120499e-002" type="0"/>
    <Peak1D F1="5.571395" intensity="1.051222e-002" type="0"/>
    <Peak1D F1="5.529656" intensity="9.812170e-003" type="0"/>
    <Peak1D F1="5.527410" intensity="9.087733e-003" type="0"/>
    <Peak1D F1="5.479312" intensity="1.711344e-002" type="0"/>
    <Peak1D F1="5.476627" intensity="1.562644e-002" type="0"/>
    <Peak1D F1="5.451793" intensity="1.182699e-002" type="0"/>
    <Peak1D F1="5.449581" intensity="1.029206e-002" type="0"/>
    <Peak1D F1="5.424452" intensity="9.985026e-003" type="0"/>
    <Peak1D F1="5.422373" intensity="9.913583e-003" type="0"/>
    <Peak1D F1="5.409421" intensity="3.746108e-003" type="0"/>
    <Peak1D F1="5.392960" intensity="2.622894e-003" type="0"/>
    <Peak1D F1="5.338153" intensity="1.577487e-003" type="0"/>
    <Peak1D F1="5.324357" intensity="1.308827e-003" type="0"/>
    <Peak1D F1="5.316009" intensity="2.010513e-003" type="0"/>
    <Peak1D F1="5.304957" intensity="2.370081e-003" type="0"/>
    <Peak1D F1="5.291833" intensity="4.988939e-003" type="0"/>
    <Peak1D F1="5.279199" intensity="8.990002e-003" type="0"/>
    <Peak1D F1="5.263933" intensity="5.290586e-001" type="0"/>
    <Peak1D F1="5.262782" intensity="5.547031e-001" type="0"/>
    <Peak1D F1="5.261752" intensity="5.219509e-001" type="0"/>
    <Peak1D F1="5.253522" intensity="2.004430e+000" type="0"/>
    <Peak1D F1="5.251341" intensity="1.904519e+000" type="0"/>
    <Peak1D F1="5.238622" intensity="4.981169e-002" type="0"/>
    <Peak1D F1="5.226316" intensity="1.940603e+000" type="0"/>
    <Peak1D F1="5.224115" intensity="1.883250e+000" type="0"/>
    <Peak1D F1="5.220149" intensity="5.510518e-001" type="0"/>
    <Peak1D F1="5.218888" intensity="5.348850e-001" type="0"/>
    <Peak1D F1="5.176247" intensity="5.518676e-002" type="0"/>
    <Peak1D F1="5.172849" intensity="1.143508e-001" type="0"/>
    <Peak1D F1="5.169334" intensity="1.473206e-001" type="0"/>
    <Peak1D F1="5.165835" intensity="1.201852e-001" type="0"/>
    <Peak1D F1="5.159165" intensity="1.247179e-001" type="0"/>
    <Peak1D F1="5.155745" intensity="2.286358e-001" type="0"/>
    <Peak1D F1="5.152315" intensity="2.942987e-001" type="0"/>
    <Peak1D F1="5.148815" intensity="2.460453e-001" type="0"/>
    <Peak1D F1="5.145216" intensity="1.515624e-001" type="0"/>
    <Peak1D F1="5.141941" intensity="1.182841e-001" type="0"/>
    <Peak1D F1="5.138773" intensity="1.419802e-001" type="0"/>
    <Peak1D F1="5.135317" intensity="1.401073e-001" type="0"/>
    <Peak1D F1="5.131784" intensity="9.262110e-002" type="0"/>
    <Peak1D F1="5.107641" intensity="4.070001e-003" type="0"/>
    <Peak1D F1="5.100187" intensity="4.363836e-003" type="0"/>
    <Peak1D F1="5.065944" intensity="4.299833e-001" type="0"/>
    <Peak1D F1="5.064384" intensity="4.402908e-001" type="0"/>
    <Peak1D F1="5.051069" intensity="2.537929e-002" type="0"/>
    <Peak1D F1="5.048708" intensity="2.621223e-002" type="0"/>
    <Peak1D F1="5.038902" intensity="4.076492e-001" type="0"/>
    <Peak1D F1="5.037349" intensity="4.323288e-001" type="0"/>
    <Peak1D F1="5.011726" intensity="7.492796e-001" type="0"/>
    <Peak1D F1="4.997240" intensity="5.618999e-001" type="0"/>
    <Peak1D F1="4.994630" intensity="6.105253e-001" type="0"/>
    <Peak1D F1="4.864319" intensity="1.972696e-003" type="0"/>
    <Peak1D F1="4.836201" intensity="4.599930e-003" type="0"/>
    <Peak1D F1="4.814653" intensity="3.409661e-003" type="0"/>
    <Peak1D F1="4.795919" intensity="5.313538e-003" type="0"/>
    <Peak1D F1="4.768213" intensity="2.381703e-003" type="0"/>
    <Peak1D F1="4.756719" intensity="2.969130e-003" type="0"/>
    <Peak1D F1="4.702466" intensity="1.166288e-002" type="0"/>
    <Peak1D F1="4.683521" intensity="7.923371e-002" type="0"/>
    <Peak1D F1="4.681596" intensity="9.531286e-002" type="0"/>
    <Peak1D F1="4.679193" intensity="7.512210e-002" type="0"/>
    <Peak1D F1="4.663316" intensity="3.803708e-003" type="0"/>
    <Peak1D F1="4.618154" intensity="5.687287e-002" type="0"/>
    <Peak1D F1="4.613949" intensity="1.072620e-001" type="0"/>
    <Peak1D F1="4.609730" intensity="5.512723e-002" type="0"/>
    <Peak1D F1="4.358345" intensity="1.813236e-002" type="0"/>
    <Peak1D F1="4.341810" intensity="3.759807e-002" type="0"/>
    <Peak1D F1="4.325289" intensity="1.850605e-002" type="0"/>
    <Peak1D F1="4.290335" intensity="1.732135e-002" type="0"/>
    <Peak1D F1="4.273539" intensity="4.231953e-002" type="0"/>
    <Peak1D F1="4.256742" intensity="3.429001e-002" type="0"/>
    <Peak1D F1="4.240160" intensity="1.083893e-002" type="0"/>
    <Peak1D F1="4.234565" intensity="3.328091e-003" type="0"/>
    <Peak1D F1="4.229090" intensity="4.170253e-003" type="0"/>
    <Peak1D F1="4.218963" intensity="7.532725e-003" type="0"/>
    <Peak1D F1="4.212543" intensity="1.033508e-002" type="0"/>
    <Peak1D F1="4.203156" intensity="1.750680e-002" type="0"/>
    <Peak1D F1="4.190969" intensity="4.049239e-002" type="0"/>
    <Peak1D F1="4.177566" intensity="3.675636e+000" type="0"/>
    <Peak1D F1="4.161032" intensity="7.512655e+000" type="0"/>
    <Peak1D F1="4.144480" intensity="3.730582e+000" type="0"/>
    <Peak1D F1="4.130920" intensity="3.851389e-002" type="0"/>
    <Peak1D F1="4.109748" intensity="3.412938e+000" type="0"/>
    <Peak1D F1="4.093077" intensity="6.964448e+000" type="0"/>
    <Peak1D F1="4.076380" intensity="3.468391e+000" type="0"/>
    <Peak1D F1="4.063364" intensity="2.838767e-002" type="0"/>
    <Peak1D F1="4.052538" intensity="1.222544e-002" type="0"/>
    <Peak1D F1="4.045713" intensity="7.514678e-003" type="0"/>
    <Peak1D F1="4.037637" intensity="2.851894e-003" type="0"/>
    <Peak1D F1="4.028262" intensity="2.488506e-003" type="0"/>
    <Peak1D F1="4.020996" intensity="1.175559e-003" type="0"/>
    <Peak1D F1="4.017693" intensity="1.560467e-003" type="0"/>
    <Peak1D F1="4.009388" intensity="9.382049e-004" type="0"/>
    <Peak1D F1="3.998246" intensity="2.565943e-003" type="0"/>
    <Peak1D F1="3.991484" intensity="1.781723e-002" type="0"/>
    <Peak1D F1="3.974930" intensity="3.744863e-002" type="0"/>
    <Peak1D F1="3.958342" intensity="1.815424e-002" type="0"/>
    <Peak1D F1="3.952848" intensity="3.672597e-003" type="0"/>
    <Peak1D F1="3.936366" intensity="2.913440e-003" type="0"/>
    <Peak1D F1="3.923875" intensity="1.646635e-002" type="0"/>
    <Peak1D F1="3.907182" intensity="3.463410e-002" type="0"/>
    <Peak1D F1="3.890480" intensity="1.679770e-002" type="0"/>
    <Peak1D F1="3.883094" intensity="2.798714e-003" type="0"/>
    <Peak1D F1="3.866555" intensity="2.375986e-003" type="0"/>
    <Peak1D F1="3.657964" intensity="2.159660e-002" type="0"/>
    <Peak1D F1="3.641551" intensity="4.430577e-002" type="0"/>
    <Peak1D F1="3.625015" intensity="2.168035e-002" type="0"/>
    <Peak1D F1="3.618419" intensity="3.640626e-003" type="0"/>
    <Peak1D F1="3.607897" intensity="3.250261e-003" type="0"/>
    <Peak1D F1="3.604921" intensity="3.208423e-003" type="0"/>
    <Peak1D F1="3.592265" intensity="2.921521e-003" type="0"/>
    <Peak1D F1="3.490709" intensity="3.797281e-002" type="0"/>
    <Peak1D F1="3.488731" intensity="3.686202e-002" type="0"/>
    <Peak1D F1="3.472687" intensity="3.719948e-003" type="0"/>
    <Peak1D F1="3.430587" intensity="1.661509e-003" type="0"/>
    <Peak1D F1="3.416997" intensity="4.511398e-003" type="0"/>
    <Peak1D F1="3.400654" intensity="6.779840e-003" type="0"/>
    <Peak1D F1="3.390231" intensity="5.972298e-003" type="0"/>
    <Peak1D F1="3.382124" intensity="1.040092e-002" type="0"/>
    <Peak1D F1="3.361262" intensity="4.759717e-002" type="0"/>
    <Peak1D F1="3.358980" intensity="5.263070e-002" type="0"/>
    <Peak1D F1="3.329991" intensity="7.425495e+000" type="0"/>
    <Peak1D F1="3.327889" intensity="7.174101e+000" type="0"/>
    <Peak1D F1="3.307031" intensity="3.301463e-002" type="0"/>
    <Peak1D F1="3.296574" intensity="1.047474e-002" type="0"/>
    <Peak1D F1="3.281172" intensity="7.233809e-003" type="0"/>
    <Peak1D F1="3.258596" intensity="1.809687e-003" type="0"/>
    <Peak1D F1="3.254730" intensity="2.477132e-003" type="0"/>
    <Peak1D F1="3.231158" intensity="9.543659e-004" type="0"/>
    <Peak1D F1="3.165667" intensity="3.889261e-002" type="0"/>
    <Peak1D F1="3.163711" intensity="3.762782e-002" type="0"/>
    <Peak1D F1="3.115063" intensity="8.238535e-002" type="0"/>
    <Peak1D F1="3.100346" intensity="1.557269e-003" type="0"/>
    <Peak1D F1="3.084502" intensity="1.668181e-003" type="0"/>
    <Peak1D F1="3.071481" intensity="1.499941e-003" type="0"/>
    <Peak1D F1="3.047520" intensity="7.190012e-002" type="0"/>
    <Peak1D F1="3.034932" intensity="3.413048e-003" type="0"/>
    <Peak1D F1="3.015636" intensity="2.662705e-003" type="0"/>
    <Peak1D F1="3.006960" intensity="7.195042e-003" type="0"/>
    <Peak1D F1="2.997001" intensity="1.162129e-002" type="0"/>
    <Peak1D F1="2.978473" intensity="1.496487e-002" type="0"/>
    <Peak1D F1="2.972663" intensity="3.115745e-002" type="0"/>
    <Peak1D F1="2.945421" intensity="1.500000e+001" type="0"/>
    <Peak1D F1="2.921464" intensity="4.129966e-002" type="0"/>
    <Peak1D F1="2.914593" intensity="2.225272e-002" type="0"/>
    <Peak1D F1="2.910014" intensity="1.806782e-002" type="0"/>
    <Peak1D F1="2.903456" intensity="3.515819e-002" type="0"/>
    <Peak1D F1="2.876857" intensity="1.274778e+001" type="0"/>
    <Peak1D F1="2.875862" intensity="1.190273e+001" type="0"/>
    <Peak1D F1="2.852659" intensity="3.493370e-002" type="0"/>
    <Peak1D F1="2.845528" intensity="1.329298e-002" type="0"/>
    <Peak1D F1="2.841282" intensity="7.376093e-003" type="0"/>
    <Peak1D F1="2.827833" intensity="9.217286e-003" type="0"/>
    <Peak1D F1="2.820089" intensity="2.841236e-003" type="0"/>
    <Peak1D F1="2.813512" intensity="2.323419e-003" type="0"/>
    <Peak1D F1="2.808776" intensity="3.079322e-003" type="0"/>
    <Peak1D F1="2.801045" intensity="3.866818e-003" type="0"/>
    <Peak1D F1="2.792493" intensity="2.065512e-003" type="0"/>
    <Peak1D F1="2.771406" intensity="8.439021e-002" type="0"/>
    <Peak1D F1="2.750750" intensity="2.117422e-003" type="0"/>
    <Peak1D F1="2.712717" intensity="2.053337e-003" type="0"/>
    <Peak1D F1="2.701849" intensity="6.887679e-002" type="0"/>
    <Peak1D F1="2.677365" intensity="2.395990e-003" type="0"/>
    <Peak1D F1="2.658683" intensity="1.297526e-003" type="0"/>
    <Peak1D F1="2.617214" intensity="1.439377e-002" type="0"/>
    <Peak1D F1="2.596208" intensity="2.320606e-003" type="0"/>
    <Peak1D F1="2.582489" intensity="2.196591e-003" type="0"/>
    <Peak1D F1="2.554004" intensity="1.767083e-003" type="0"/>
    <Peak1D F1="2.540036" intensity="1.243181e-003" type="0"/>
    <Peak1D F1="2.510594" intensity="1.282905e-003" type="0"/>
    <Peak1D F1="2.441302" intensity="9.495617e-004" type="0"/>
    <Peak1D F1="2.408299" intensity="8.499501e-003" type="0"/>
    <Peak1D F1="2.399709" intensity="1.930074e-003" type="0"/>
    <Peak1D F1="2.381578" intensity="4.156786e-003" type="0"/>
    <Peak1D F1="2.359445" intensity="2.680597e-002" type="0"/>
    <Peak1D F1="2.354037" intensity="1.763769e-002" type="0"/>
    <Peak1D F1="2.331080" intensity="2.251847e-002" type="0"/>
    <Peak1D F1="2.326000" intensity="3.291326e-002" type="0"/>
    <Peak1D F1="2.320935" intensity="2.196931e-002" type="0"/>
    <Peak1D F1="2.303621" intensity="5.088929e-003" type="0"/>
    <Peak1D F1="2.287127" intensity="7.814054e-003" type="0"/>
    <Peak1D F1="2.283187" intensity="8.146108e-003" type="0"/>
    <Peak1D F1="2.260676" intensity="1.036171e-002" type="0"/>
    <Peak1D F1="2.250163" intensity="9.542869e-002" type="0"/>
    <Peak1D F1="2.239739" intensity="1.595660e-001" type="0"/>
    <Peak1D F1="2.226057" intensity="3.629182e-001" type="0"/>
    <Peak1D F1="2.220663" intensity="3.828726e-001" type="0"/>
    <Peak1D F1="2.217773" intensity="3.320273e-001" type="0"/>
    <Peak1D F1="2.208900" intensity="8.440688e-001" type="0"/>
    <Peak1D F1="2.199191" intensity="4.208557e-001" type="0"/>
    <Peak1D F1="2.184431" intensity="4.447325e-001" type="0"/>
    <Peak1D F1="2.168994" intensity="2.359957e-001" type="0"/>
    <Peak1D F1="2.149874" intensity="6.606002e-002" type="0"/>
    <Peak1D F1="2.147068" intensity="6.311529e-002" type="0"/>
    <Peak1D F1="2.144660" intensity="5.961552e-002" type="0"/>
    <Peak1D F1="2.101924" intensity="1.703793e-002" type="0"/>
    <Peak1D F1="2.091089" intensity="1.656018e-002" type="0"/>
    <Peak1D F1="2.070333" intensity="3.252532e-002" type="0"/>
    <Peak1D F1="2.059803" intensity="3.090546e-002" type="0"/>
    <Peak1D F1="2.048816" intensity="1.638030e-002" type="0"/>
    <Peak1D F1="2.040339" intensity="2.831432e-002" type="0"/>
    <Peak1D F1="2.032096" intensity="2.028410e-002" type="0"/>
    <Peak1D F1="2.004092" intensity="1.718932e-002" type="0"/>
    <Peak1D F1="1.993872" intensity="1.805980e-002" type="0"/>
    <Peak1D F1="1.990594" intensity="2.168614e-002" type="0"/>
    <Peak1D F1="1.986842" intensity="1.832994e-002" type="0"/>
    <Peak1D F1="1.970665" intensity="6.312027e-003" type="0"/>
    <Peak1D F1="1.960899" intensity="7.320164e-003" type="0"/>
    <Peak1D F1="1.937042" intensity="6.223843e-003" type="0"/>
    <Peak1D F1="1.920230" intensity="6.704006e-003" type="0"/>
    <Peak1D F1="1.904851" intensity="6.207057e-003" type="0"/>
    <Peak1D F1="1.881541" intensity="3.523127e-002" type="0"/>
    <Peak1D F1="1.860895" intensity="2.525610e-002" type="0"/>
    <Peak1D F1="1.852166" intensity="3.202093e-002" type="0"/>
    <Peak1D F1="1.848783" intensity="3.118675e-002" type="0"/>
    <Peak1D F1="1.836609" intensity="2.833318e-002" type="0"/>
    <Peak1D F1="1.828961" intensity="3.489270e-002" type="0"/>
    <Peak1D F1="1.820837" intensity="4.645890e-002" type="0"/>
    <Peak1D F1="1.802263" intensity="5.013116e-002" type="0"/>
    <Peak1D F1="1.762195" intensity="4.452093e-001" type="0"/>
    <Peak1D F1="1.740724" intensity="1.238654e-001" type="0"/>
    <Peak1D F1="1.733463" intensity="1.085063e-001" type="0"/>
    <Peak1D F1="1.718774" intensity="7.100856e+000" type="0"/>
    <Peak1D F1="1.712754" intensity="4.527385e-001" type="0"/>
    <Peak1D F1="1.696678" intensity="2.234106e+000" type="0"/>
    <Peak1D F1="1.694330" intensity="2.160191e+000" type="0"/>
    <Peak1D F1="1.681962" intensity="7.330992e-001" type="0"/>
    <Peak1D F1="1.665562" intensity="1.837551e+000" type="0"/>
    <Peak1D F1="1.657931" intensity="6.112466e-001" type="0"/>
    <Peak1D F1="1.649155" intensity="1.926692e+000" type="0"/>
    <Peak1D F1="1.647296" intensity="2.291447e+000" type="0"/>
    <Peak1D F1="1.644191" intensity="1.402541e+000" type="0"/>
    <Peak1D F1="1.641344" intensity="1.378216e+000" type="0"/>
    <Peak1D F1="1.627558" intensity="2.160974e+000" type="0"/>
    <Peak1D F1="1.622784" intensity="2.035953e+000" type="0"/>
    <Peak1D F1="1.621562" intensity="1.987139e+000" type="0"/>
    <Peak1D F1="1.610404" intensity="3.429953e+000" type="0"/>
    <Peak1D F1="1.606657" intensity="3.612572e+000" type="0"/>
    <Peak1D F1="1.598531" intensity="1.288989e+000" type="0"/>
    <Peak1D F1="1.584633" intensity="1.989236e+000" type="0"/>
    <Peak1D F1="1.567919" intensity="9.040156e-001" type="0"/>
    <Peak1D F1="1.552350" intensity="5.966791e-002" type="0"/>
    <Peak1D F1="1.535621" intensity="4.459887e-002" type="0"/>
    <Peak1D F1="1.528824" intensity="2.283146e-002" type="0"/>
    <Peak1D F1="1.518738" intensity="1.964350e-002" type="0"/>
    <Peak1D F1="1.508787" intensity="2.020805e-002" type="0"/>
    <Peak1D F1="1.490886" intensity="2.059912e-002" type="0"/>
    <Peak1D F1="1.487765" intensity="1.779225e-002" type="0"/>
    <Peak1D F1="1.481869" intensity="1.510949e-002" type="0"/>
    <Peak1D F1="1.476125" intensity="2.074390e-002" type="0"/>
    <Peak1D F1="1.471097" intensity="1.966248e-002" type="0"/>
    <Peak1D F1="1.461105" intensity="2.159886e-002" type="0"/>
    <Peak1D F1="1.445690" intensity="4.768818e-001" type="0"/>
    <Peak1D F1="1.427122" intensity="1.516004e+000" type="0"/>
    <Peak1D F1="1.413358" intensity="1.232282e+000" type="0"/>
    <Peak1D F1="1.408177" intensity="2.231679e+000" type="0"/>
    <Peak1D F1="1.394996" intensity="2.274384e+000" type="0"/>
    <Peak1D F1="1.389222" intensity="2.429270e+000" type="0"/>
    <Peak1D F1="1.380958" intensity="9.846520e-001" type="0"/>
    <Peak1D F1="1.376208" intensity="2.523309e+000" type="0"/>
    <Peak1D F1="1.371142" intensity="1.788110e+000" type="0"/>
    <Peak1D F1="1.362528" intensity="9.290618e-001" type="0"/>
    <Peak1D F1="1.357245" intensity="2.285123e+000" type="0"/>
    <Peak1D F1="1.344227" intensity="3.961125e-001" type="0"/>
    <Peak1D F1="1.338985" intensity="1.432294e+000" type="0"/>
    <Peak1D F1="1.320721" intensity="4.302598e-001" type="0"/>
    <Peak1D F1="1.315592" intensity="6.284786e-002" type="0"/>
    <Peak1D F1="1.304130" intensity="2.847132e-002" type="0"/>
    <Peak1D F1="1.294718" intensity="2.496562e-002" type="0"/>
    <Peak1D F1="1.272716" intensity="2.509121e-002" type="0"/>
    <Peak1D F1="1.262613" intensity="2.522341e-002" type="0"/>
    <Peak1D F1="1.255522" intensity="1.779500e-002" type="0"/>
    <Peak1D F1="1.249565" intensity="1.659899e-002" type="0"/>
    <Peak1D F1="1.241402" intensity="1.392618e-002" type="0"/>
    <Peak1D F1="1.235778" intensity="1.616414e-002" type="0"/>
    <Peak1D F1="1.230788" intensity="2.192004e-002" type="0"/>
    <Peak1D F1="1.224141" intensity="9.095119e-003" type="0"/>
    <Peak1D F1="1.217513" intensity="1.536361e-002" type="0"/>
    <Peak1D F1="1.212345" intensity="1.176141e-002" type="0"/>
    <Peak1D F1="1.198453" intensity="1.376863e-002" type="0"/>
    <Peak1D F1="1.180078" intensity="9.494943e-003" type="0"/>
    <Peak1D F1="1.161670" intensity="3.630246e-003" type="0"/>
    <Peak1D F1="1.141374" intensity="2.213697e-003" type="0"/>
    <Peak1D F1="1.124666" intensity="2.323338e-003" type="0"/>
    <Peak1D F1="1.112884" intensity="2.925897e-002" type="0"/>
    <Peak1D F1="1.097313" intensity="3.705316e-002" type="0"/>
    <Peak1D F1="1.094594" intensity="6.232742e-002" type="0"/>
    <Peak1D F1="1.079297" intensity="6.140604e-002" type="0"/>
    <Peak1D F1="1.060897" intensity="2.340576e-002" type="0"/>
    <Peak1D F1="1.050578" intensity="4.209790e-003" type="0"/>
    <Peak1D F1="1.043870" intensity="5.519537e-003" type="0"/>
    <Peak1D F1="1.036676" intensity="4.417720e-003" type="0"/>
    <Peak1D F1="1.031061" intensity="1.870735e-002" type="0"/>
    <Peak1D F1="1.022984" intensity="5.767622e-002" type="0"/>
    <Peak1D F1="1.013952" intensity="2.051496e-002" type="0"/>
    <Peak1D F1="1.010089" intensity="1.301893e-002" type="0"/>
    <Peak1D F1="1.002610" intensity="1.160067e-002" type="0"/>
    <Peak1D F1="0.995112" intensity="1.719534e-002" type="0"/>
    <Peak1D F1="0.991852" intensity="1.811884e-002" type="0"/>
    <Peak1D F1="0.986475" intensity="2.508453e-002" type="0"/>
    <Peak1D F1="0.977629" intensity="4.784497e-002" type="0"/>
    <Peak1D F1="0.958636" intensity="5.818426e+000" type="0"/>
    <Peak1D F1="0.943302" intensity="6.908960e+000" type="0"/>
    <Peak1D F1="0.940209" intensity="1.212744e+001" type="0"/>
    <Peak1D F1="0.924991" intensity="1.216262e+001" type="0"/>
    <Peak1D F1="0.921864" intensity="5.690444e+000" type="0"/>
    <Peak1D F1="0.906572" intensity="4.801891e+000" type="0"/>
    <Peak1D F1="0.882877" intensity="2.834458e-002" type="0"/>
    <Peak1D F1="0.876114" intensity="1.964494e-002" type="0"/>
    <Peak1D F1="0.864971" intensity="1.032880e-002" type="0"/>
    <Peak1D F1="0.858360" intensity="9.213815e-003" type="0"/>
    <Peak1D F1="0.853343" intensity="8.352497e-003" type="0"/>
    <Peak1D F1="0.849431" intensity="8.338662e-003" type="0"/>
    <Peak1D F1="0.841328" intensity="4.622203e-003" type="0"/>
    <Peak1D F1="0.830779" intensity="5.189616e-003" type="0"/>
    <Peak1D F1="0.814925" intensity="2.545407e-002" type="0"/>
    <Peak1D F1="0.800596" intensity="3.495676e-002" type="0"/>
    <Peak1D F1="0.797092" intensity="2.737415e-002" type="0"/>
    <Peak1D F1="0.785310" intensity="3.973623e-002" type="0"/>
    <Peak1D F1="0.782175" intensity="6.804839e-002" type="0"/>
    <Peak1D F1="0.766961" intensity="7.011995e-002" type="0"/>
    <Peak1D F1="0.763647" intensity="3.984607e-002" type="0"/>
    <Peak1D F1="0.760851" intensity="6.456386e-002" type="0"/>
    <Peak1D F1="0.748581" intensity="2.903219e-002" type="0"/>
    <Peak1D F1="0.733920" intensity="2.930372e-003" type="0"/>
    <Peak1D F1="0.712187" intensity="4.396311e-003" type="0"/>
    <Peak1D F1="0.691887" intensity="3.706333e-003" type="0"/>
    <Peak1D F1="0.631089" intensity="3.557032e-003" type="0"/>
    <Peak1D F1="0.611398" intensity="3.756991e-003" type="0"/>
    <Peak1D F1="0.589653" intensity="2.004186e-003" type="0"/>
    <Peak1D F1="0.146155" intensity="1.373920e-002" type="0"/>
    <Peak1D F1="0.094280" intensity="9.340500e-003" type="0"/>
    <Peak1D F1="0.072745" intensity="2.068546e-003" type="0"/>
    <Peak1D F1="0.060632" intensity="9.819863e-004" type="0"/>
    <Peak1D F1="0.052464" intensity="1.502433e-003" type="0"/>
    <Peak1D F1="0.040168" intensity="1.282446e-003" type="0"/>
    <Peak1D F1="0.033691" intensity="1.483958e-003" type="0"/>
    <Peak1D F1="0.028133" intensity="4.904649e-003" type="0"/>
    <Peak1D F1="0.021580" intensity="4.136229e-003" type="0"/>
    <Peak1D F1="0.008043" intensity="1.240854e-001" type="0"/>
    <Peak1D F1="-0.000124" intensity="3.728746e+000" type="0"/>
    <Peak1D F1="-0.008409" intensity="1.104152e-001" type="0"/>
    <Peak1D F1="-0.023868" intensity="7.747905e-003" type="0"/>
    <Peak1D F1="-0.030556" intensity="2.326011e-003" type="0"/>
    <Peak1D F1="-0.047857" intensity="1.265428e-003" type="0"/>
    <Peak1D F1="-0.149345" intensity="1.346624e-002" type="0"/>
  </PeakList1D>
</PeakList>
